risac.v
module risac (
  input						clk, rst_n,
  output	[31:0] 	oIbusAddr,
  input		[31:0] 	iIbusData,
  input		[31:0]	iIbusIAddr,
  input						iIbusWait,
  output          oIbusRead,
  
  output	[31:0]	oDbusAddr,
  output					oDbusWe,
  output	[31:0]	oDbusData,
  output					oDbusRead,
  output	[3:0]		oDbusByteEn,
  input		[31:0]	iDbusData,
  input						iDbusWait
);

  // ===========================================================
  // the instruction address generation logic
  // pc contains the byte address
  reg [31:0] pc;
  reg [31:0] branchTarget;
  reg branch;
  reg dataHazard;
  reg stallPipe;
  reg pcChanged;
  
  assign oIbusAddr = pc;
  // wait for waitrequest to fall before zeroing
  // read (i.e.) wait till a pending request is completed
  assign oIbusRead = iIbusWait ? 1'b1 : pcChanged;

  always @ (posedge clk or negedge rst_n) begin: IF
    if (!rst_n) begin 
      pc <= 'b0;
      pcChanged <= 'b1;
    end	else if (!stallPipe && !dataHazard | branch) begin 
      // new data arrives when wait is 0
      // so update pc when wait is 0
      pc <= iIbusWait ? pc : (branch ? branchTarget : pc + 3'd4);

      // assert read regardless of wait
      // but only when pc is updated
      // also dont deassert when wait is high
      // pcChanged <= iIbusWait ? 1'b0 : 1'b1;
      if (!iIbusWait) begin 
        pcChanged <= 1'b1;
      end else begin 
        pcChanged <= 1'b0;
      end
    end else begin
      pcChanged <= 1'b0;
    end
  end

  // ===========================================================
  // decode the instruction 
  // for now support only rtype, itype and stype

  reg [3:0]		aluOpDec;
  reg [4:0]		rs1Dec, rs2Dec, rdDec;
  reg [31:0]	immDec, pcDec, rs1ShiftDec, rs2ShiftDec, rdShiftDec;
  reg 				validDec;
  reg					immSelDec;
  reg 				rdWeDec;
  reg					illegalDec;
  reg					lDec, sDec, luipcDec, luiDec;
  reg         branchDec;
  reg         branchType;
  reg					jalr;

  always @ (posedge clk or negedge rst_n) begin: DEC
    if (!rst_n) begin 
      {aluOpDec, rs1Dec, rs2Dec, immDec, validDec, immSelDec, rdShiftDec} <= 'b0;
      {rdWeDec, illegalDec, pcDec, lDec, sDec, rs1ShiftDec, rs2ShiftDec} <= 'b0; 
      {luipcDec, luiDec, branchDec, branchType, jalr} <= 'b0;
    end else if (!stallPipe && !dataHazard) begin 
      // the address of the currently being decoded instruction
      pcDec			<= iIbusIAddr;

      // the instruction is valid if there is not wait signal
      validDec	<= ~iIbusWait;

      // decode the instruction regardless of validity

      // branch instructions
      // only branch opcodes begin with 110
      branchDec   <= iIbusData[6:4] == 3'b110;
      // for conditional branches, the next 2 bits are zero
      // branchType: zero for unconditional, 1 for conditional
      // for all branches, pc <= pc + offset
      // except jalr, pc <= rs1 + offset 
      branchType  <= iIbusData[3:2] == 2'b00;
      jalr <= iIbusData[3:2] == 2'b01;

      // lui and auipc are special
      luipcDec <= iIbusData[4:2] == 3'b101;
      luiDec   <= iIbusData[5:2] == 4'b1101;

      // alu op is always [14:12]
      aluOpDec[2:0]	<= iIbusData[14:12];
      aluOpDec[3]		<= iIbusData[30];

      // rs1, rs2 and rd are fixed
      rs1Dec			<= iIbusData[19:15];
      rs2Dec			<= iIbusData[24:20];
      rs1ShiftDec	<= 1 << iIbusData[19:15];
      rs2ShiftDec <= 1 << iIbusData[24:20];
      rdDec				<= iIbusData[11:7];
      rdShiftDec 	<= 1 << iIbusData[11:7];

      // always write to rd except when storing or conditional branching
      // all instructions except stores and conditional branches have 4:2 
      // not equal to zero
      rdWeDec		<= (iIbusData[4:2] != 3'b000);
      
      // select imm when instr[6:4] == 001
      // in rv32i, no other instruction has opcode[6:4] == 001 other than those
      // that use imm
      // lui also uses imm
      // jalr and jal also use imm
      immSelDec	<=  (iIbusData[6:4] == 3'b001) | 
                    (iIbusData[6:2] == 5'b01101) | 
                    (iIbusData[6:2] == 5'b11011) |
                    (iIbusData[6:2] == 5'b11001);

      // for the imm, use the opcode
      case (iIbusData[6:2]) // the last 2 bits are always 1 anyway
      
      // itype load
      5'b00000: immDec <= { {21{iIbusData[31]}}, iIbusData[30:20] };
      // itype alu
      5'b00100: immDec <= { {21{iIbusData[31]}}, iIbusData[30:20] };
      // jalr
      5'b11001: immDec <= { {21{iIbusData[31]}}, iIbusData[30:20] };
      
      // SType: store
      5'b01000: immDec <= { {21{iIbusData[31]}}, iIbusData[30:25], iIbusData[11:7] };

      // lui
      5'b01101: immDec <= { iIbusData[31:12], 12'b0 };
      // auipc
      5'b00101: immDec <= { iIbusData[31:12], 12'b0 };
      // jal
      5'b11011: immDec <= { {12{iIbusData[31]}}, iIbusData[19:12], iIbusData[20], iIbusData[30:25], iIbusData[24:21], 1'b0 };

      // btype, all conditional branches
      5'b11000: immDec <= { {20{iIbusData[31]}}, iIbusData[7], iIbusData[30:25], iIbusData[11:8], 1'b0 };

      endcase

      // load when all zero opcode
      lDec <= iIbusData[6:2] == 5'b00000;
      sDec <= iIbusData[6:2] == 5'b01000;

      // for now ignore the illegal instruction
      // TODO: add illegal indication
    end
  end

  // ===========================================================
  // fetch the operands from the register file
  // the register file has registered outputs

  // also maintain a RAT to track which registers are dirty
  // if dirty registers are needed, stall the previous stages
  // till clean value arrives and invalidate all the instructions
  // that are sent forward 

  reg [31:0]	registers [0:31];
  reg [31:0]	rs1Data, rs2Data, rdShiftEx;
  
  // data hazard handling mech
  reg [31:0]  rat [0:1];
  reg 				stallDataHazard;
  reg         falseAlarm;
  reg [1:0]   sourceEqual;

  reg 				validEx, rdWeEx;
	reg [2:0]   invalidRegister;

  integer idx;

  always @ (posedge clk or negedge rst_n) begin: RAT
    if (!rst_n) begin 
      rat[0] <= 'b0;
      rat[1] <= 'b0;
      falseAlarm <= 'b0;
      sourceEqual <= 'b0;
    end else if (!stallPipe) begin
      // update rat
      // set rd'th bit to 1 in rat[0..1]
      // if it is 1 then set it 1 anyway
      // set the rdEx'th bit to 0 in rat[0..1]
      // setting 1 takes priority

      // the zero register is always clean
      rat[0][0] <= 1'b0;
      rat[1][0] <= 1'b0;

      // on the condition that if rat[rd] is already 1 then 
      // 1. add x2, x1, x3
      // 2. add x2, x2, x4
      // when 1 is written back, rat[2] is set to 1 instead of 0
      // because 2 will force it
      // in this case, we must allow only 1 instruction to pass
      // we use a false alarm bit for this

      // raise false alarm when rdDec == rdEx and all the valid conditions
      // also set false alarm to zero if it is one
      if (falseAlarm) begin 
        falseAlarm <= 'b0;
        sourceEqual<= 'b0;
      end else if (rdWeDec && validDec && rdWeEx && validEx) begin 
        falseAlarm <= rdEx == rdDec;
        sourceEqual<= {(rs1Dec == rdEx), (rs2Dec == rdDec)};
      end

      for (idx = 1; idx < 32; idx = idx + 1) begin
        // there is also a false alarm when after a branch instruction is decoded,
        // another instruction sets the rat which is invalidated after the branch is taken
        // but the rat remains there and is not fixed

        // the code below fixes this by zeroing the rat set by the instructions currently in
        // of and dec
        if (branch) begin 
          if (rdOf == idx && validOf && rdWeOf) begin 
            // the possible instructions that set the rat are now in of
            // the instruction in dec can set the rat
            rat[0][idx] <= 1'b0;
            rat[1][idx] <= 1'b0;
          end 
          else if (rdDec == idx && validDec && rdWeDec) begin 
            rat[0][idx] <= 1'b0;
            rat[1][idx] <= 1'b0;
          end
        end 
        // if the register to be updated [(rdDecWe == 1) and (rdShiftDec[idx] == 1)]
        // then set the rat to 1 
        else if (rdWeDec && rdShiftDec[idx] && validDec && !dataHazard && !(|invalidRegister[1:0])) begin 
          rat[0][idx] <= 1'b1;
          rat[1][idx] <= 1'b1;
        end
        // else if the register is *being* updated [(rdExWe == 1) and (rdShiftEx[idx] == 1)]
        // then set the rat to 0
        else if (rdWeEx && rdShiftEx[idx] && validEx) begin 
          rat[0][idx] <= 1'b0;
          rat[1][idx] <= 1'b0;
        end			
      end
    end
  end

  // combinational part 
  reg rs1booked;
  reg rs2booked;
  always @ (*) begin: DATA_HAZARD_DETECTION
    // check if rs1 and rs2 are 'booked'
    // TODO: maybe take a look at this again
    // rs1 is booked if rat[0] is set and the instruction is not
    // lui, auipc
    rs1booked = |(rs1ShiftDec & rat[0]) && ~luipcDec;
    // rs2 is booked if rat[1] is set and the instruction is not 
    // one that uses imm
    rs2booked = |(rs2ShiftDec & rat[1]) && ~immSelDec;

    
    // data hazard occurs when rs1 or rs2 is booked and nothing is being written
    // to the regfile 
    // if there is data being written to the reg file then no need to stall, let it
    // pass
    dataHazard = falseAlarm ? (rs1booked & sourceEqual[1]) | (rs2booked & sourceEqual[0]) : ((rs1booked) | (rs2booked));
  end
  
  // when the data hazard occurs, set valid to zero and stall previous stages

  // propogate the rdWe, valid, aluOp, immSel, pc and imm signals
  reg					validOf, rdWeOf, immSelOf;	
  reg [31:0]	immOf, pcOf;
  reg [3:0]		aluOpOf;
  reg [4:0]		rdOf;
  reg 				lOf, sOf, luipcOf;
  reg         branchOf, compareOf;
  reg [31:0]	bTargetOf, branchOffset;

  always @ (posedge clk or negedge rst_n) begin: OF
    if (!rst_n) begin 
      {rs1Data, rs2Data, validOf, rdWeOf, immOf} <= 'b0;
      {pcOf, immSelOf, aluOpOf, rdOf, lOf, sOf, luipcOf, branchOf} <= 'b0;
      {compareOf, bTargetOf, branchOffset} <= 'b0;
      // !do not reset the registers!!

    end else if (!stallPipe) begin 
      // propogation
      {rdWeOf} <= {rdWeDec};
      {immSelOf, rdOf} <= {immSelDec, rdDec};
      {lOf, sOf, luipcOf} <= {lDec, sDec, luipcDec};

      // branch handles
      // branchOf signal is high when the branch is unconditional
      // e.g. jal, jalr
      branchOf <= branchDec & ~branchType;
      // compareOf is high when the branch is a conditional branch
      // e.g. bne, ...
      compareOf<= branchDec & branchType;
      
      bTargetOf<= jalr ? (rs1Dec == 5'b0 ? 32'b0 : registers [rs1Dec]) : pcDec;
      branchOffset <= immDec;

      if (falseAlarm) begin 
        validOf <= validDec;
      end else begin 
        validOf <= validDec & ~dataHazard;
      end 

      rs1Data <= rs1Dec == 5'b0 ? 32'b0 : registers [rs1Dec];
      rs2Data	<= rs2Dec == 5'b0 ? 32'b0 : registers [rs2Dec];
      aluOpOf <= luipcDec | (branchDec & ~branchType) ? 4'b0 : aluOpDec;
      pcOf    <= luiDec ? 32'b0 : pcDec;
      immOf   <= (branchDec & ~branchType) ? 32'd4 : immDec;
    end
  end

  // ============================================================
  // select the operands to feed the alu and lsu
  // add the imm in rs1 to get the address
  // the data to store is in rs2


  reg [31:0] 	aluIn1, aluIn2;

  // propogate the valid, aluOp, rdWe, pc
  reg [31:0] 	pcOs;
  reg [3:0]		aluOpOs;
  reg 				validOs, rdWeOs;
  reg [4:0]		rdOs;
  reg 				lOs, sOs;
  reg [31:0]	lsuAddrOs, lsuDataOs;
  
  // the branch compare signals
	reg					compareResult;
	
	
	// the branch comparators
	always @ (*) begin: BRANCH_COMPARATOR
    case (aluOpOf[2:0])
    3'b000: 	compareResult = rs1Data == rs2Data;
    3'b001: 	compareResult = rs1Data != rs2Data;
    3'b100: 	compareResult = $signed(rs1Data) <  $signed(rs2Data);
    3'b101: 	compareResult = $signed(rs1Data) >= $signed(rs2Data);
    3'b110: 	compareResult = rs1Data <  rs2Data;
    3'b111: 	compareResult = rs1Data >= rs2Data;
    default: compareResult = 1'b0;
    endcase
  end
	
	// the branch hazard handling technique
	// invalidate 3 instructions if the branch
	// is taken
	
	
	always @ (posedge clk or negedge rst_n) begin: BRANCH_HANDLER
    if (!rst_n) begin 
      invalidRegister <= 'b0;
    end else if (!stallPipe) begin 
      invalidRegister[0] <= ((compareResult & compareOf) | branchOf) & validOf;
      invalidRegister[1] <= invalidRegister[0];
      invalidRegister[2] <= invalidRegister[1];
    end
  end
	
  always @ (posedge clk or negedge rst_n) begin: OS
    if (!rst_n) begin 
      {pcOs, aluOpOs, validOs, rdWeOs, rdOs} <= 'b0;
      {aluIn1, aluIn2, lOs, sOs, lsuAddrOs, lsuDataOs} <= 'b0;
      {branch, branchTarget} <= 'b0;
    end else if (!stallPipe) begin 
      {pcOs, rdWeOs, rdOs} <= {pcOf, rdWeOf, rdOf};
      {lOs, sOs} <= {lOf, sOf};

      // the branch unit
      // branch only if instruction was unconditional branch
      // and if it was conditional then branch if the condition met

      branch <= (branchOf | (compareResult & compareOf)) & validOf;
			branchTarget <= bTargetOf + branchOffset;
			validOs <= (|invalidRegister) ? 1'b0 : validOf;

      lsuAddrOs <= rs1Data + immOf;
      lsuDataOs <= rs2Data;

      // when lui comes, the imm is the value 
      // so zero aluIn1 and set operation to add
      aluIn1	<= (luipcOf | branchOf) ? pcOf : rs1Data;

      // aluIn2 is between imm and rs2Data
      aluIn2	<= immSelOf ? immOf : rs2Data;

      // if IType and the operation is add then clear op[3],
      // coz there is no subi 
      if (immSelOf && (aluOpOf[2:0] == 3'b000))
        aluOpOs[3] <= 1'b0;
      else 
        aluOpOs[3] <= aluOpOf[3];

      aluOpOs[2:0] <= aluOpOf[2:0]; 
    end
  end

  // ============================================================
  // the execute stage
  // can have multiple units in paralell
  // for now we only have the alu and lsu 
  reg [31:0] exRes;

  // propogate the valid, pc, rdWe
  reg [31:0]	pcEx;
  reg [4:0]		rdEx;

  always @ (posedge clk or negedge rst_n) begin: EX
    if (!rst_n) begin 
      {pcEx, validEx, rdWeEx, rdEx, rdShiftEx} <= 'b0;
    end else if (!stallPipe) begin
      {pcEx, validEx, rdWeEx, rdEx} <= {pcOs, validOs, rdWeOs, rdOs};
      rdShiftEx <= 1 << rdOs;			
    end
  end

  // ============================================================
  // the alu has a fixed latency of 1
  // the alu causes no stalls
  reg [31:0]	aluRes;

  always @ (posedge clk or negedge rst_n) begin: EX_ALU
    if (!rst_n) begin 
      aluRes <= 'b0;
    end else begin 
      case (aluOpOs[2:0])
      3'b000: aluRes <= aluOpOs[3] ? aluIn1 - aluIn2 : aluIn1 + aluIn2;	// add/sub
      3'b001: aluRes <= aluIn1 << aluIn2[4:0];	// sll
      3'b010: aluRes <= $signed(aluIn1) < $signed(aluIn2) ? 32'b1 : 32'b0; 
      3'b011: aluRes <= aluIn1 < aluIn2 ? 32'b1 : 32'b0;
      3'b100: aluRes <= aluIn1 ^ aluIn2;
      3'b101: aluRes <= aluOpOs[3] ? $signed($signed(aluIn1) >>> aluIn2[4:0]) : aluIn1 >> aluIn2[4:0];
      3'b110: aluRes <= aluIn1 | aluIn2;
      3'b111: aluRes <= aluIn1 & aluIn2;
      endcase
    end 
  end

  // ============================================================
  // the lsu has min latency of 1 
  // max latency of infinity
  // lsu can stall the pipeline 
  // data to store in rs2

  reg [31:0]	lsuRes;
  reg 				lsuStall;
  reg [3:0]		lsuByteEn;
  reg 				lEx;

  assign oDbusAddr 		= lsuAddrOs;
  assign oDbusRead 		= lOs & validOs;
  assign oDbusWe	 		= sOs & validOs;
  assign oDbusData 		= lsuDataOs;
  assign oDbusByteEn 	= lsuByteEn;

  // wait only asserted when reading, writing does not assert wait
  // from m4k, reads have min latency of 1

  always @ (*) begin: EX_LSU_BYTEENABLE_GENERATOR
    lsuStall = iDbusWait & (lOs | sOs) & validOs;
  
    case (aluOpOs[1:0]) 
    2'b00:	lsuByteEn = 4'b1;			// sb/lb
    2'b01:	lsuByteEn = 4'b11;		// sh/lh
    2'b10:	lsuByteEn	= 4'b1111;	// sw/lw
    default:lsuByteEn = 4'b0;	
    endcase
  end

  always @ (posedge clk or negedge rst_n) begin: EX_LSU
    if (!rst_n) begin 
      lsuRes 	<= 'b0;
      lEx 		<= 'b0;
    end	else if (!stallPipe) begin 
      lEx 		<= lOs;
      if (aluOpOs[1]) begin  // lw
        lsuRes <= iDbusData;
      end else begin 
        case ({aluOpOs[2], aluOpOs[0]}) 
        2'b00: lsuRes <= { {24{iDbusData[07]}}, iDbusData[07:0] };	// lb
        2'b01: lsuRes <= { {16{iDbusData[15]}}, iDbusData[15:0] };	// lh
        2'b10: lsuRes <= { 24'b0, iDbusData[07:0] };	// lbu
        2'b11: lsuRes <= { 16'b0, iDbusData[15:0] };	// lhu 
        endcase
      end
    end
  end

  // ============================================================
  // the stall handling mech,
  // simply or the stalls from all the sources
  // for now, only lsu can stall
  // IF doesn't stall, it keeps sending invalid instructions
  // which don't affect anything

  always @ (*) begin: EX_LSU_STALL_GENERATOR
    stallPipe = lsuStall;
  end	

  // ============================================================
  // the write back stage

  // mux the result from various stages
  // for now, if load instruction, then select lsuRes
  always @ (*) begin: WB_MUX
    exRes	= lEx ? lsuRes : aluRes;
  end

  always @ (posedge clk) begin: WB_REGISTER_FILE
    // do not reset the register file
    // write back if valid only
    if (validEx && rdWeEx) begin 
      registers[rdEx] <= exRes;
    end
  end
endmodule

testbench/risac_tb_single_mem.v
`timescale 1ns / 1ps

module testbench();

  reg						clk = 1, rst_n = 0;
  wire	[31:0] 	oIbusAddr;
  reg		[31:0] 	iIbusData;
  reg		[31:0]	iIbusIAddr;
  reg						iIbusWait;
  
  wire	[31:0]	oDbusAddr;
  wire					oDbusWe;
  wire	[31:0]	oDbusData;
  wire					oDbusRead;
  wire	[3:0]		oDbusByteEn;
  reg		[31:0]	iDbusData;
  reg						iDbusWait;

  wire  [31:0]  rat0, rat1;

  risac u_risac (
    .clk          (clk),
    .rst_n        (rst_n),

    // The IBUS

    .oIbusAddr    (oIbusAddr),
    .iIbusData    (iIbusData),
    .iIbusIAddr   (iIbusIAddr),
    .iIbusWait    (iIbusWait),
    
    // The DBUS

    .oDbusAddr    (oDbusAddr),
    .oDbusWe      (oDbusWe),
    .oDbusData    (oDbusData),
    .oDbusRead    (oDbusRead),
    .oDbusByteEn  (oDbusByteEn),
    .iDbusData    (iDbusData),
    .iDbusWait    (iDbusWait)
  );

  assign rat0 = u_risac.rat[0];
  assign rat1 = u_risac.rat[1];

  reg [7:0] mem [0:4095]; // 4K ram
  reg [31:0] cnt = 0;

  // create a clock
  always @ (posedge clk) begin 
    cnt = cnt + 1;
  end

  always begin 
    #10 
    clk = !clk;
  end

  // initialize the memories
  integer i;
  initial begin 
    // prepare a vcd dump
    $dumpfile("risac2.vcd");
    $dumpvars(0, testbench);
    $readmemh("program.vh", mem);

    $display ("\n======================");
    $display ("RISCV Virtual Terminal");
    $display ("======================\n"); 
    
    #5
    rst_n = 1'b1;



    #10000 
    // dump memory to output 
    $display ("======================\n"); 
    
    $finish;
  end

  // create a memory system
  // simple zero latency memory

  // ==========================
  // the instruction bus
  // ==========================
  reg [31:0] instr;
  always @ (oIbusAddr) begin 
    iIbusWait = 1'b0;
    instr = {mem [oIbusAddr+3], mem [oIbusAddr+2], mem [oIbusAddr+1], mem [oIbusAddr]};
    if (instr === 32'hxxxxxxxx) begin 
      instr = 32'b0;
    end
    iIbusData = instr;
    iIbusIAddr = oIbusAddr;
  end


  reg [7:0]  dmem_addr;
  reg [31:0] and_mask;

  always @ (cnt) begin 
    // the virtual console 
    if (oDbusWe && oDbusAddr == 32'h1000000 && oDbusByteEn[0]) begin 
      $write("%c", oDbusData[7:0]);		
    end
  end 

  reg [31:0] oldWord;

  always @ (*) begin 
    iDbusData = 'b0;
    iDbusWait = 'b0;
    
    if (oDbusWe) begin 
      mem[oDbusAddr]     = oDbusByteEn[0] ? oDbusData[07:00] : mem[oDbusAddr];
      mem[oDbusAddr + 1] = oDbusByteEn[1] ? oDbusData[15:08] : mem[oDbusAddr + 1];
      mem[oDbusAddr + 2] = oDbusByteEn[2] ? oDbusData[23:16] : mem[oDbusAddr + 2];
      mem[oDbusAddr + 3] = oDbusByteEn[3] ? oDbusData[31:24] : mem[oDbusAddr + 3];
    end
    
    if (oDbusRead) begin 
      if (oDbusAddr == 32'h1000004) begin  
      iDbusData = 32'h00402000;      
      end else begin 
      iDbusData = {mem[oDbusAddr + 3], mem[oDbusAddr + 2], mem[oDbusAddr + 1], mem[oDbusAddr]};
      end
    end
  end

endmodule

testbench/risac2.vcd
$date
	Tue Nov 26 12:26:47 2019
$end
$version
	Icarus Verilog
$end
$timescale
	1ps
$end
$scope module testbench $end
$var wire 32 ! rat0 [31:0] $end
$var wire 32 " rat1 [31:0] $end
$var wire 32 # oIbusAddr [31:0] $end
$var wire 1 $ oDbusWe $end
$var wire 1 % oDbusRead $end
$var wire 32 & oDbusData [31:0] $end
$var wire 4 ' oDbusByteEn [3:0] $end
$var wire 32 ( oDbusAddr [31:0] $end
$var reg 1 ) clk $end
$var reg 32 * cnt [31:0] $end
$var reg 32 + iDbusData [31:0] $end
$var reg 1 , iDbusWait $end
$var reg 32 - iIbusData [31:0] $end
$var reg 32 . iIbusIAddr [31:0] $end
$var reg 1 / iIbusWait $end
$var reg 32 0 instr [31:0] $end
$var reg 1 1 rst_n $end
$scope module u_risac $end
$var wire 1 ) clk $end
$var wire 32 2 iDbusData [31:0] $end
$var wire 1 , iDbusWait $end
$var wire 32 3 iIbusData [31:0] $end
$var wire 32 4 iIbusIAddr [31:0] $end
$var wire 1 / iIbusWait $end
$var wire 32 5 oDbusAddr [31:0] $end
$var wire 4 6 oDbusByteEn [3:0] $end
$var wire 32 7 oDbusData [31:0] $end
$var wire 1 % oDbusRead $end
$var wire 1 $ oDbusWe $end
$var wire 32 8 oIbusAddr [31:0] $end
$var wire 1 1 rst_n $end
$var wire 1 9 oIbusRead $end
$var reg 32 : aluIn1 [31:0] $end
$var reg 32 ; aluIn2 [31:0] $end
$var reg 4 < aluOpDec [3:0] $end
$var reg 4 = aluOpOf [3:0] $end
$var reg 4 > aluOpOs [3:0] $end
$var reg 32 ? aluRes [31:0] $end
$var reg 32 @ bTargetOf [31:0] $end
$var reg 1 A branch $end
$var reg 1 B branchDec $end
$var reg 1 C branchOf $end
$var reg 32 D branchOffset [31:0] $end
$var reg 32 E branchTarget [31:0] $end
$var reg 1 F branchType $end
$var reg 1 G compareOf $end
$var reg 1 H compareResult $end
$var reg 1 I dataHazard $end
$var reg 32 J exRes [31:0] $end
$var reg 1 K falseAlarm $end
$var reg 1 L illegalDec $end
$var reg 32 M immDec [31:0] $end
$var reg 32 N immOf [31:0] $end
$var reg 1 O immSelDec $end
$var reg 1 P immSelOf $end
$var reg 3 Q invalidRegister [2:0] $end
$var reg 1 R jalr $end
$var reg 1 S lDec $end
$var reg 1 T lEx $end
$var reg 1 U lOf $end
$var reg 1 V lOs $end
$var reg 32 W lsuAddrOs [31:0] $end
$var reg 4 X lsuByteEn [3:0] $end
$var reg 32 Y lsuDataOs [31:0] $end
$var reg 32 Z lsuRes [31:0] $end
$var reg 1 [ lsuStall $end
$var reg 1 \ luiDec $end
$var reg 1 ] luipcDec $end
$var reg 1 ^ luipcOf $end
$var reg 32 _ pc [31:0] $end
$var reg 1 ` pcChanged $end
$var reg 32 a pcDec [31:0] $end
$var reg 32 b pcEx [31:0] $end
$var reg 32 c pcOf [31:0] $end
$var reg 32 d pcOs [31:0] $end
$var reg 5 e rdDec [4:0] $end
$var reg 5 f rdEx [4:0] $end
$var reg 5 g rdOf [4:0] $end
$var reg 5 h rdOs [4:0] $end
$var reg 32 i rdShiftDec [31:0] $end
$var reg 32 j rdShiftEx [31:0] $end
$var reg 1 k rdWeDec $end
$var reg 1 l rdWeEx $end
$var reg 1 m rdWeOf $end
$var reg 1 n rdWeOs $end
$var reg 32 o rs1Data [31:0] $end
$var reg 5 p rs1Dec [4:0] $end
$var reg 32 q rs1ShiftDec [31:0] $end
$var reg 1 r rs1booked $end
$var reg 32 s rs2Data [31:0] $end
$var reg 5 t rs2Dec [4:0] $end
$var reg 32 u rs2ShiftDec [31:0] $end
$var reg 1 v rs2booked $end
$var reg 1 w sDec $end
$var reg 1 x sOf $end
$var reg 1 y sOs $end
$var reg 2 z sourceEqual [1:0] $end
$var reg 1 { stallPipe $end
$var reg 1 | validDec $end
$var reg 1 } validEx $end
$var reg 1 ~ validOf $end
$var reg 1 !" validOs $end
$var integer 32 "" idx [31:0] $end
$scope begin BRANCH_COMPARATOR $end
$upscope $end
$scope begin BRANCH_HANDLER $end
$upscope $end
$scope begin DATA_HAZARD_DETECTION $end
$upscope $end
$scope begin DEC $end
$upscope $end
$scope begin EX $end
$upscope $end
$scope begin EX_ALU $end
$upscope $end
$scope begin EX_LSU $end
$upscope $end
$scope begin EX_LSU_BYTEENABLE_GENERATOR $end
$upscope $end
$scope begin EX_LSU_STALL_GENERATOR $end
$upscope $end
$scope begin IF $end
$upscope $end
$scope begin OF $end
$upscope $end
$scope begin OS $end
$upscope $end
$scope begin RAT $end
$upscope $end
$scope begin WB_MUX $end
$upscope $end
$scope begin WB_REGISTER_FILE $end
$upscope $end
$upscope $end
$upscope $end
$enddefinitions $end
#0
$dumpvars
bx ""
0!"
0~
0}
0|
0{
b0 z
0y
0x
0w
0v
b0 u
b0 t
b0 s
0r
b0 q
b0 p
b0 o
0n
0m
0l
0k
b0 j
b0 i
b0 h
b0 g
b0 f
bx e
b0 d
b0 c
b0 b
b0 a
1`
b0 _
0^
0]
0\
0[
b0 Z
b0 Y
b1 X
b0 W
0V
0U
0T
0S
0R
b0 Q
0P
0O
b0 N
b0 M
0L
0K
b0 J
0I
1H
0G
0F
b0 E
b0 D
0C
0B
0A
b0 @
b0 ?
b0 >
b0 =
b0 <
b0 ;
b0 :
19
b0 8
b0 7
b1 6
b0 5
b0 4
b1000100010111 3
b0 2
01
b1000100010111 0
0/
b0 .
b1000100010111 -
0,
b0 +
b0 *
1)
b0 (
b1 '
b0 &
0%
0$
b0 #
b0 "
b0 !
$end
#5000
11
#10000
0)
#20000
b100 .
b100 4
b10000000100010011 -
b10000000100010011 3
b10000000100010011 0
b1 j
bx g
b1000000000000 M
1O
1k
b100 i
b10 e
b1 u
b1 q
b1 <
1]
1R
1|
b100 #
b100 8
b100 _
b1 *
b100000 ""
1)
#30000
0)
#40000
1I
1r
b1000 .
b1000 4
b10110000000000000001101111 -
b10110000000000000001101111 3
b10110000000000000001101111 0
bx h
b1000000000000 N
1~
b1000000000000 D
1^
1P
b10 g
1m
b100 "
b100 !
b0 M
b100 q
b10 p
b0 <
0]
0R
1F
b100 a
b1000 #
b1000 8
b1000 _
b10 *
b100000 ""
1)
#50000
0)
#60000
xH
09
bx j
bx f
b1000000000000 ;
b1000000000000 (
b1000000000000 5
b1000000000000 W
1!"
b1000000000000 E
1n
b10 h
b0 N
b100 c
bx o
0~
b0 D
b100 @
0^
0`
b11 *
b100000 ""
1)
#70000
0)
#80000
b1000000000000 J
b1000000000000 ?
b100 j
1}
1l
b10 f
b0 ;
bx :
bx (
bx 5
bx W
0!"
b100 E
b100 d
b100 *
b100000 ""
1)
#90000
0)
#100000
bx J
0I
0r
bx ?
b100 b
0}
b0 "
b0 !
b10 z
1K
b101 *
b100000 ""
1)
#110000
0)
#120000
0H
19
b1100 .
b1100 4
b10110000000101001001100011 -
b10110000000101001001100011 3
b10110000000101001001100011 0
b1000000000000 o
1~
b100 "
b100 !
b0 z
0K
b101100 M
b1 i
b0 e
b1000000000000 u
b1 q
b1100 t
b0 p
0F
1B
b1000 a
1`
b1100 #
b1100 8
b1100 _
b110 *
b100000 ""
1)
#130000
0)
#140000
xH
b10000 .
b10000 4
b110001011000011100110011 -
b110001011000011100110011 3
b110001011000011100110011 0
b1000000000000 :
b1000000000000 (
b1000000000000 5
b1000000000000 W
1!"
b100 N
b1000 c
bx s
b0 o
b101100 D
b1000 @
1C
b0 g
b100100 M
0O
0k
b10000 i
b100 e
b101 <
1F
b1100 a
b10000 #
b10000 8
b10000 _
b111 *
b100000 ""
1)
#150000
0)
#160000
b1000000000000 J
b10100 .
b10100 4
b10001010010011110000011 -
b10001010010011110000011 3
b10001010010011110000011 0
b1000000000000 ?
1}
b100 ;
b1000 :
bx &
bx 7
bx Y
b100 (
b100 5
b100 W
b110100 E
1A
b1000 d
b0 h
b1 Q
b100100 N
b1100 c
b101 =
b100100 D
b1100 @
1G
0C
0P
b100 g
0m
1k
b100000000000000 i
b1110 e
b100000000000 q
b1011 p
b0 <
0B
b10000 a
b10100 #
b10100 8
b10100 _
b1000 *
b100000 ""
1)
#170000
0)
#180000
b1100 J
b11 '
b11 6
b11 X
b110100 .
b110100 4
b11111111000000010000000100010011 -
b11111111000000010000000100010011 3
b11111111000000010000000100010011 0
b1100 ?
b1 j
b1000 b
b0 f
b101 >
bx ;
b0 :
b100100 (
b100100 5
b100100 W
0!"
b110000 E
0A
b1100 d
0n
b100 h
b1x Q
b10000 c
b0 =
bx o
0~
b10000 @
0G
b1110 g
1m
b0 "
b0 !
1S
b100 M
0k
b1000000000000000 i
b1111 e
b10000 u
b10000000000 q
b100 t
b1010 p
b10 <
0|
b10100 a
b110100 #
b110100 8
b110100 _
b1001 *
b100000 ""
1)
#190000
0)
#200000
bx J
b1 '
b1 6
b1 X
0H
b111000 .
b111000 4
b100010010011000100011 -
b100010010011000100011 3
b100010010011000100011 0
bx ?
b10000 j
b1100 b
0}
0l
b100 f
b0 >
bx :
bx (
bx 5
bx W
b110100 E
b10000 d
1n
b1110 h
b1x0 Q
b100 N
b10100 c
b10 =
b100 D
b10100 @
1U
b1111 g
0m
0S
b11111111111111111111111111110000 M
1O
1k
b100 i
b10 e
b10000000000000000 u
b100 q
b10000 t
b10 p
b1000 <
1|
b110100 a
b111000 #
b111000 8
b111000 _
b1010 *
b100000 ""
1)
#210000
0)
#220000
b1111 '
b1111 6
b1111 X
xH
b111100 .
b111100 4
b10000000000000011101111 -
b10000000000000011101111 3
b10000000000000011101111 0
b100000000000000 j
b10000 b
1l
b1110 f
b10 >
b11000 E
1V
b10100 d
0n
b1111 h
bx00 Q
b11111111111111111111111111110000 N
b110100 c
b1000 =
b1000000000000 o
1~
b11111111111111111111111111110000 D
b110100 @
0U
1P
b10 g
1m
1w
b1100 M
0O
0k
b1000000000000 i
b1100 e
b10 u
b1 t
b10 <
b111000 a
b111100 #
b111100 8
b111100 _
b1011 *
b100000 ""
1)
#230000
0)
