risac.v
module risac (
	input						clk, rst_n,
	output	[31:0] 	oIbusAddr,
	input		[31:0] 	iIbusData,
	input		[31:0]	iIbusIAddr,
	input						iIbusWait,
	
	output	[31:0]	oDbusAddr,
	output					oDbusWe,
	output	[31:0]	oDbusData,
	output					oDbusRead,
	output	[3:0]		oDbusByteEn,
	input		[31:0]	iDbusData,
	input						iDbusWait
);

	// ===========================================================
	// the instruction address generation logic
	// pc contains the byte address
	reg [31:0]	pc;
	reg dataHazard;
	reg stallPipe;
	
	assign oIbusAddr = pc;

	always @ (posedge clk or negedge rst_n) begin 
		if (!rst_n) begin 
			pc <= 'b0;
		end	else if (!stallPipe && !dataHazard) begin 
			// for now increment pc when the memory is ready
			pc <= iIbusWait ? pc : pc + 3'd4;		
		end 
	end

	// ===========================================================
	// decode the instruction 
	// for now support only rtype, itype and stype

	reg [3:0]		aluOpDec;
	reg [4:0]		rs1Dec, rs2Dec, rdDec;
	reg [31:0]	immDec, pcDec, rs1ShiftDec, rs2ShiftDec, rdShiftDec;
	reg 				validDec;
	reg					immSelDec;
	reg 				rdWeDec;
	reg					illegalDec;
	reg					lDec, sDec;

	always @ (posedge clk or negedge rst_n) begin 
		if (!rst_n) begin 
			{aluOpDec, rs1Dec, rs2Dec, immDec, validDec, immSelDec, rdShiftDec} <= 'b0;
			{rdWeDec, illegalDec, pcDec, lDec, sDec, rs1ShiftDec, rs2ShiftDec} <= 'b0;
		end else if (!stallPipe && !dataHazard) begin 
			// the address of the currently being decoded instruction
			pcDec			<= iIbusIAddr;

			// the instruction is valid if there is not wait signal
			validDec	<= ~iIbusWait;

			// decode the instruction regardless of validity
			
			// alu op is always [14:12]
			aluOpDec[2:0]	<= iIbusData[14:12];
			aluOpDec[3]		<= iIbusData[30];

			// rs1, rs2 and rd are fixed
			rs1Dec			<= iIbusData[19:15];
			rs2Dec			<= iIbusData[24:20];
			rs1ShiftDec	<= 1 << iIbusData[19:15];
			rs2ShiftDec <= 1 << iIbusData[24:20];
			rdDec				<= iIbusData[11:7];
			rdShiftDec 	<= 1 << iIbusData[11:7];

			// always write to rd except when storing or branching
			// we cater only stores for now 
			rdWeDec		<= iIbusData[6:0] != 7'b0100011;
			
			// select imm when instr[6:4] == 001
			// in rv32i, no other instruction has opcode[6:4] == 001 other than those
			// that use imm
			immSelDec	<= (iIbusData[6:4] == 3'b001);

			// for the imm, use the opcode
			case (iIbusData[6:2]) // the last 2 bits are always 1 anyway
			
			// itype load
			5'b00000: immDec <= { {21{iIbusData[31]}}, iIbusData[30:20] };
			// itype alu
			5'b00100: immDec <= { {21{iIbusData[31]}}, iIbusData[30:20] };
			//jalr
			5'b11001: immDec <= { {21{iIbusData[31]}}, iIbusData[30:20] };
			
			// SType: store
			5'b01000: immDec <= { {21{iIbusData[31]}}, iIbusData[30:25], iIbusData[11:7] };

			endcase

			// load when all zero opcode
			lDec <= iIbusData[6:2] == 5'b00000;
			sDec <= iIbusData[6:2] == 5'b01000;

			// for now ignore the illegal instruction
			// TODO: add illegal indication
		end
	end

	// ===========================================================
	// fetch the operands from the register file
	// the register file has registered outputs

	// also maintain a RAT to track which registers are dirty
	// if dirty registers are needed, stall the previous stages
	// till clean value arrives and invalidate all the instructions
	// that are sent forward 

	reg [31:0]	registers [0:31];
	reg [31:0]	rs1Data, rs2Data, rdShiftEx;
	
	// data hazard handling mech
	reg [31:0]  rat [0:1];
	reg 				stallDataHazard;

	reg 				validEx, rdWeEx;

	integer idx;

	always @ (posedge clk or negedge rst_n) begin: RAT
		if (!rst_n) begin 
			rat[0] <= 'b0;
			rat[1] <= 'b0;
		end else if (!stallPipe) begin
			// update rat
			// set rd'th bit to 1 in rat[0..1]
			// if it is 1 then set it 1 anyway
			// set the rdEx'th bit to 0 in rat[0..1]
			// setting 1 takes priority

			// the zero register is always clean
			rat[0][0] <= 1'b0;
			rat[1][0] <= 1'b0;

			for (idx = 1; idx < 32; idx = idx + 1) begin
				// if the register to be updated [(rdDecWe == 1) and (rdShiftDec[idx] == 1)]
				// then set the rat to 1 
				if (rdWeDec && rdShiftDec[idx] && validDec) begin 
					rat[0][idx] <= 1'b1;
					rat[1][idx] <= 1'b1;
				end
				// else if the register is *being* updated [(rdExWe == 1) and (rdShiftEx[idx] == 1)]
				// then set the rat to 0
				else if (rdWeEx && rdShiftEx[idx] && validEx) begin 
					rat[0][idx] <= 1'b0;
					rat[1][idx] <= 1'b0;
				end				
			end
		end
	end

	// combinational part 
	reg rs1booked;
	reg rs2booked;
	always @ (*) begin 
		// check if rs1 and rs2 are 'booked'
		rs1booked = |(rs1ShiftDec & rat[0]);
		rs2booked = |(rs2ShiftDec & rat[1]) && ~immSelDec;

		// rs1booked = rat[0][rs1Dec];
		// rs2booked = rat[1][rs2Dec] && ~immSelDec;
		dataHazard = rs1booked | rs2booked;
	end
	
	// when the data hazard occurs, set valid to zero and stall previous stages

	// propogate the rdWe, valid, aluOp, immSel, pc and imm signals
	reg					validOf, rdWeOf, immSelOf;	
	reg [31:0]	immOf, pcOf;
	reg [3:0]		aluOpOf;
	reg [4:0]		rdOf;
	reg 				lOf, sOf;

	always @ (posedge clk or negedge rst_n) begin 
		if (!rst_n) begin 
			{rs1Data, rs2Data, validOf, rdWeOf, immOf} <= 'b0;
			{pcOf, immSelOf, aluOpOf, rdOf, lOf, sOf} <= 'b0;
			// !do not reset the registers!!

		end else if (!stallPipe) begin 
			// propogation
			{validOf, rdWeOf, immOf} <= {validDec & ~dataHazard, rdWeDec, immDec};
			{pcOf, immSelOf, aluOpOf, rdOf} <= {pcDec, immSelDec, aluOpDec, rdDec};
			{lOf, sOf} <= {lDec, sDec};

			rs1Data <= rs1Dec == 5'b0 ? 32'b0 : registers [rs1Dec];
			rs2Data	<= rs2Dec == 5'b0 ? 32'b0 : registers [rs2Dec];
		end
	end

	// ============================================================
	// select the operands to feed the alu and lsu
	// add the imm in rs1 to get the address
	// the data to store is in rs2


	reg [31:0] 	aluIn1, aluIn2;

	// propogate the valid, aluOp, rdWe, pc
	reg [31:0] 	pcOs;
	reg [3:0]		aluOpOs;
	reg 				validOs, rdWeOs;
	reg [4:0]		rdOs;
	reg 				lOs, sOs;
	reg [31:0]	lsuAddrOs, lsuDataOs;

	always @ (posedge clk or negedge rst_n) begin 
		if (!rst_n) begin 
			{pcOs, aluOpOs, validOs, rdWeOs, rdOs} <= 'b0;
			{aluIn1, aluIn2, lOs, sOs, lsuAddrOs, lsuDataOs} <= 'b0;
		end else if (!stallPipe) begin 
			{pcOs, validOs, rdWeOs, rdOs} <= {pcOf, validOf, rdWeOf, rdOf};
			{lOs, sOs} <= {lOf, sOf};

			lsuAddrOs <= rs1Data + immOf;
			lsuDataOs <= rs2Data;

			// for now aluIn1 is just rs1Data
			aluIn1	<= rs1Data;

			// aluIn2 is between imm and rs2Data
			aluIn2	<= immSelOf ? immOf : rs2Data;

			// if IType and the operation is add then clear op[3],
			// coz there is no subi 
			if (immSelOf && (aluOpOf[2:0] == 3'b000))
				aluOpOs[3] <= 1'b0;
			else 
				aluOpOs[3] <= aluOpOf[3];

			aluOpOs[2:0] <= aluOpOf[2:0]; 
		end
	end

	// ============================================================
	// the execute stage
	// can have multiple units in paralell
	// for now we only have the alu and lsu 
	reg [31:0] exRes;

	// propogate the valid, pc, rdWe
	reg [31:0]	pcEx;
	reg [4:0]		rdEx;

	always @ (posedge clk or negedge rst_n) begin 
		if (!rst_n) begin 
			{pcEx, validEx, rdWeEx, rdEx, rdShiftEx} <= 'b0;
		end else if (!stallPipe) begin
			{pcEx, validEx, rdWeEx, rdEx} <= {pcOs, validOs, rdWeOs, rdOs};
			rdShiftEx <= 1 << rdOs;			
		end
	end

	// ============================================================
	// the alu has a fixed latency of 1
	// the alu causes no stalls
	reg [31:0]	aluRes;

	always @ (posedge clk or negedge rst_n) begin 
		if (!rst_n) begin 
			aluRes <= 'b0;
		end else begin 
			case (aluOpOs[2:0])
			3'b000: aluRes <= aluOpOs[3] ? aluIn1 - aluIn2 : aluIn1 + aluIn2;	// add/sub
			3'b001: aluRes <= aluIn1 << aluIn2[4:0];	// sll
			3'b010: aluRes <= $signed(aluIn1) < $signed(aluIn2) ? 32'b1 : 32'b0; 
			3'b011: aluRes <= aluIn1 < aluIn2 ? 32'b1 : 32'b0;
			3'b100: aluRes <= aluIn1 ^ aluIn2;
			3'b101: aluRes <= aluOpOs[3] ? $signed($signed(aluIn1) >>> aluIn2[4:0]) : aluIn1 >> aluIn2[4:0];
			3'b110: aluRes <= aluIn1 | aluIn2;
			3'b111: aluRes <= aluIn1 & aluIn2;
			endcase
		end 
	end

	// ============================================================
	// the lsu has min latency of 1 
	// max latency of infinity
	// lsu can stall the pipeline 
	// data to store in rs2

	reg [31:0]	lsuRes;
	reg 				lsuStall;
	reg [3:0]		lsuByteEn;
	reg 				lEx;

	assign oDbusAddr 		= lsuAddrOs;
	assign oDbusRead 		= lOs & validOs;
	assign oDbusWe	 		= sOs & validOs;
	assign oDbusData 		= lsuDataOs;
	assign oDbusByteEn 	= lsuByteEn;

	// wait only asserted when reading, writing does not assert wait
	// from m4k, reads have min latency of 1

	always @ (*) begin 
		lsuStall = iDbusWait & (lOs | sOs) & validOs;
	
		case (aluOpOs[1:0]) 
		2'b00:	lsuByteEn = 4'b1;			// sb/lb
		2'b01:	lsuByteEn = 4'b11;		// sh/lh
		2'b10:	lsuByteEn	= 4'b1111;	// sw/lw
		default:lsuByteEn = 4'b0;	
		endcase
	end

	always @ (posedge clk or negedge rst_n) begin 
		if (!rst_n) begin 
			lsuRes 	<= 'b0;
			lEx 		<= 'b0;
		end	else if (!stallPipe) begin 
			lEx 		<= lOs;
			if (aluOpOs[1]) begin  // lw
				lsuRes <= iDbusData;
			end else begin 
				case ({aluOpOs[2], aluOpOs[0]}) 
				2'b00: lsuRes <= { {24{iDbusData[07]}}, iDbusData[07:0] };	// lb
				2'b01: lsuRes <= { {16{iDbusData[15]}}, iDbusData[15:0] };	// lh
				2'b10: lsuRes <= { 24'b0, iDbusData[07:0] };	// lbu
				2'b11: lsuRes <= { 16'b0, iDbusData[15:0] };	// lhu 
				endcase
			end
		end
	end

	// ============================================================
	// the stall handling mech,
	// simply or the stalls from all the sources
	// for now, only lsu can stall
	// IF doesn't stall, it keeps sending invalid instructions
	// which don't affect anything

	always @ (*) begin 
		stallPipe = lsuStall;
	end	

	// ============================================================
	// the write back stage

	// mux the result from various stages
	// for now, if load instruction, then select lsuRes
	always @ (*) begin 
		exRes	= lEx ? lsuRes : aluRes;
	end

	always @ (posedge clk) begin 
		// do not reset the register file
		// write back if valid only
		if (validEx && rdWeEx) begin 
			registers[rdEx] <= exRes;
		end
	end
endmodule

testbench/risac_tb.v
`timescale 1ns / 1ps

module testbench();

	reg						clk = 1, rst_n = 0;
	wire	[31:0] 	oIbusAddr;
	reg		[31:0] 	iIbusData;
	reg		[31:0]	iIbusIAddr;
	reg						iIbusWait;
	
	wire	[31:0]	oDbusAddr;
	wire					oDbusWe;
	wire	[31:0]	oDbusData;
	wire					oDbusRead;
	wire	[3:0]		oDbusByteEn;
	reg		[31:0]	iDbusData;
	reg						iDbusWait;

	risac u_risac (
		.clk          (clk),
		.rst_n        (rst_n),

		// The IBUS

		.oIbusAddr    (oIbusAddr),
		.iIbusData    (iIbusData),
		.iIbusIAddr   (iIbusIAddr),
		.iIbusWait    (iIbusWait),
		
		// The DBUS

		.oDbusAddr    (oDbusAddr),
		.oDbusWe      (oDbusWe),
		.oDbusData    (oDbusData),
		.oDbusRead    (oDbusRead),
		.oDbusByteEn  (oDbusByteEn),
		.iDbusData    (iDbusData),
		.iDbusWait    (iDbusWait)
	);


	reg [31:0] imem [0:255];
	reg [31:0] dmem [0:255];
	reg [31:0] cnt = 0;

	// create a clock
	always @ (posedge clk) begin 
		cnt = cnt + 1;
	end

	always begin 
		#10 
		clk = !clk;
	end

	// initialize the memories
	integer i;
	initial begin 
		// prepare a vcd dump
		$dumpfile("risac.vcd");
		$dumpvars(0, testbench);

		$readmemh("imem.hex", imem);
		$readmemh("dmem.hex", dmem);

		$display ("\n======================");
		$display ("RISCV Virtual Terminal");
		$display ("======================\n"); 
		
		#5
		rst_n = 1'b1;



		#5000 
		// dump memory to output 
		$display ("======================\n"); 
		$display ("dmem dump (first 10 words)");
		for (i = 0; i < 10; i=i+1) begin 
			$display("dmem[%0d] = 0x%x", i, dmem[i]);
		end
		
		$finish;
	end

	// create a memory system
	// simple zero latency memory

	// ==========================
	// the instruction bus
	// ==========================

	always @ (oIbusAddr) begin 
		iIbusWait <= 1'b0;
		iIbusData <= imem [oIbusAddr[9:2]];
		iIbusIAddr<= oIbusAddr;
	end


	reg [7:0]  dmem_addr;
	reg [31:0] and_mask;

	always @ (cnt) begin 
		// the virtual console 
		if (oDbusWe && oDbusAddr == 32'b0 && oDbusByteEn[0]) begin 
			$write("%c", oDbusData[7:0]);		
		end
	end 

	reg [31:0] oldWord;

	always @ (*) begin 
		iDbusData = 'b0;
		iDbusWait = 'b0;
		dmem_addr = oDbusAddr[9:2];

		if (oDbusWe) begin 
			oldWord = dmem[dmem_addr];

			if (oDbusByteEn == 4'h1) begin 
				case (oDbusAddr[1:0]) 
				2'd0: dmem[dmem_addr][07:00] = oDbusData[7:0];
				2'd1: dmem[dmem_addr][15:08] = oDbusData[7:0];
				2'd2: dmem[dmem_addr][23:16] = oDbusData[7:0];
				2'd3: dmem[dmem_addr][31:24] = oDbusData[7:0];
				endcase
			end else if (oDbusByteEn == 4'h3) begin 
				case (oDbusAddr[1])
				1'd0: dmem[dmem_addr][15:00] = oDbusData[15:0];
				1'd1: dmem[dmem_addr][31:16] = oDbusData[15:0];
				endcase
			end else if (oDbusByteEn == 4'hf) begin 
				dmem[dmem_addr] = oDbusData;
			end
		end
		
		if (oDbusRead) begin 
			iDbusData = dmem[dmem_addr];
		end
	end

endmodule

testbench/risac.vcd
$date
	Thu Nov 14 21:25:51 2019
$end
$version
	Icarus Verilog
$end
$timescale
	1ps
$end
$scope module testbench $end
$var wire 32 ! oIbusAddr [31:0] $end
$var wire 1 " oDbusWe $end
$var wire 1 # oDbusRead $end
$var wire 32 $ oDbusData [31:0] $end
$var wire 4 % oDbusByteEn [3:0] $end
$var wire 32 & oDbusAddr [31:0] $end
$var reg 1 ' clk $end
$var reg 32 ( cnt [31:0] $end
$var reg 8 ) dmem_addr [7:0] $end
$var reg 32 * iDbusData [31:0] $end
$var reg 1 + iDbusWait $end
$var reg 32 , iIbusData [31:0] $end
$var reg 32 - iIbusIAddr [31:0] $end
$var reg 1 . iIbusWait $end
$var reg 32 / oldWord [31:0] $end
$var reg 1 0 rst_n $end
$var integer 32 1 i [31:0] $end
$scope module u_risac $end
$var wire 1 ' clk $end
$var wire 32 2 iDbusData [31:0] $end
$var wire 1 + iDbusWait $end
$var wire 32 3 iIbusData [31:0] $end
$var wire 32 4 iIbusIAddr [31:0] $end
$var wire 1 . iIbusWait $end
$var wire 32 5 oDbusAddr [31:0] $end
$var wire 4 6 oDbusByteEn [3:0] $end
$var wire 32 7 oDbusData [31:0] $end
$var wire 1 # oDbusRead $end
$var wire 1 " oDbusWe $end
$var wire 32 8 oIbusAddr [31:0] $end
$var wire 1 0 rst_n $end
$var reg 32 9 aluIn1 [31:0] $end
$var reg 32 : aluIn2 [31:0] $end
$var reg 4 ; aluOpDec [3:0] $end
$var reg 4 < aluOpOf [3:0] $end
$var reg 4 = aluOpOs [3:0] $end
$var reg 32 > aluRes [31:0] $end
$var reg 1 ? dataHazard $end
$var reg 32 @ exRes [31:0] $end
$var reg 1 A illegalDec $end
$var reg 32 B immDec [31:0] $end
$var reg 32 C immOf [31:0] $end
$var reg 1 D immSelDec $end
$var reg 1 E immSelOf $end
$var reg 1 F lDec $end
$var reg 1 G lEx $end
$var reg 1 H lOf $end
$var reg 1 I lOs $end
$var reg 32 J lsuAddrOs [31:0] $end
$var reg 4 K lsuByteEn [3:0] $end
$var reg 32 L lsuDataOs [31:0] $end
$var reg 32 M lsuRes [31:0] $end
$var reg 1 N lsuStall $end
$var reg 32 O pc [31:0] $end
$var reg 32 P pcDec [31:0] $end
$var reg 32 Q pcEx [31:0] $end
$var reg 32 R pcOf [31:0] $end
$var reg 32 S pcOs [31:0] $end
$var reg 5 T rdDec [4:0] $end
$var reg 5 U rdEx [4:0] $end
$var reg 5 V rdOf [4:0] $end
$var reg 5 W rdOs [4:0] $end
$var reg 32 X rdShiftDec [31:0] $end
$var reg 32 Y rdShiftEx [31:0] $end
$var reg 1 Z rdWeDec $end
$var reg 1 [ rdWeEx $end
$var reg 1 \ rdWeOf $end
$var reg 1 ] rdWeOs $end
$var reg 32 ^ rs1Data [31:0] $end
$var reg 5 _ rs1Dec [4:0] $end
$var reg 32 ` rs1ShiftDec [31:0] $end
$var reg 1 a rs1booked $end
$var reg 32 b rs2Data [31:0] $end
$var reg 5 c rs2Dec [4:0] $end
$var reg 32 d rs2ShiftDec [31:0] $end
$var reg 1 e rs2booked $end
$var reg 1 f sDec $end
$var reg 1 g sOf $end
$var reg 1 h sOs $end
$var reg 1 i stallPipe $end
$var reg 1 j validDec $end
$var reg 1 k validEx $end
$var reg 1 l validOf $end
$var reg 1 m validOs $end
$var integer 32 n idx [31:0] $end
$scope begin RAT $end
$upscope $end
$upscope $end
$upscope $end
$enddefinitions $end
#0
$dumpvars
bx n
0m
0l
0k
0j
0i
0h
0g
0f
0e
b0 d
b0 c
b0 b
0a
b0 `
b0 _
b0 ^
0]
0\
0[
0Z
b0 Y
b0 X
b0 W
b0 V
b0 U
bx T
b0 S
b0 R
b0 Q
b0 P
b0 O
0N
b0 M
b0 L
b1 K
b0 J
0I
0H
0G
0F
0E
0D
b0 C
b0 B
0A
b0 @
0?
b0 >
b0 =
b0 <
b0 ;
b0 :
b0 9
b0 8
b0 7
b1 6
b0 5
b0 4
b100100000000000010100010011 3
b0 2
bx 1
00
bx /
0.
b0 -
b100100000000000010100010011 ,
0+
b0 *
b0 )
b0 (
1'
b0 &
b1 %
b0 $
0#
0"
b0 !
$end
#5000
10
#10000
0'
#20000
b100 -
b100 4
b101000000010000000100011 ,
b101000000010000000100011 3
b1 Y
bx V
b1001000 B
1D
1Z
b10000000000 X
b1010 T
b100000000 d
b1 `
b1000 c
1j
b100 !
b100 8
b100 O
b1 (
b100000 n
1'
#30000
0'
#40000
b1000 -
b1000 4
b110010100000000010100010011 ,
b110010100000000010100010011 3
1?
1e
b1000 !
b1000 8
b1000 O
1f
b0 B
0D
0Z
b1 X
b0 T
b10000000000 d
b1010 c
b10 ;
b100 P
bx b
1E
b1010 V
1l
1\
b1001000 C
bx W
b10 (
b100000 n
1'
#50000
0'
#60000
b10010 )
bx Y
bx U
b1001000 :
bx $
bx 7
bx L
b1001000 &
b1001000 5
b1001000 J
1m
1]
b1010 W
1g
b100 R
0E
b10 <
b0 V
0l
0\
b0 C
b11 (
b100000 n
1'
#70000
0'
#80000
b1111 %
b1111 6
b1111 K
b0 )
b1001000 @
b10 =
bx :
b0 &
b0 5
b0 J
1h
b100 S
0m
0]
b0 W
b10000000000 Y
1k
1[
b1010 U
b1001000 >
b100 (
b100000 n
1'
#90000
0'
#100000
0?
0e
b0x @
b0x >
b1 Y
b100 Q
0k
0[
b0 U
b101 (
b100000 n
1'
#110000
0'
#120000
b1100 -
b1100 4
b101000000010000000100011 ,
b101000000010000000100011 3
b1100 !
b1100 8
b1100 O
0f
b1100101 B
1D
1Z
b10000000000 X
b1010 T
b100000 d
b101 c
b0 ;
b1000 P
b1001000 b
1l
b110 (
b100000 n
1'
#130000
0'
#140000
b10000 -
b10000 4
b110110000000000010100010011 ,
b110110000000000010100010011 3
b0 /
1"
1?
1e
b1001000 :
b1001000 $
b1001000 7
b1001000 L
1m
bx b
0g
b1000 R
1E
b0 <
b1010 V
1\
b1100101 C
1f
b0 B
0D
0Z
b1 X
b0 T
b10000000000 d
b1010 c
b10 ;
b1100 P
b10000 !
b10000 8
b10000 O
b111 (
b100000 n
1'
#150000
0'
#160000
b1 %
b1 6
b1 K
b11001 )
0"
b1 @
b1001000 b
1g
b1100 R
0E
b10 <
b0 V
0l
0\
b0 C
b0 =
b1100101 :
bx $
bx 7
bx L
b1100101 &
b1100101 5
b1100101 J
0h
b1000 S
1]
b1010 W
1k
b1 >
b1000 (
b100000 n
1'
#170000
0'
#180000
b1100101 @
b1111 %
b1111 6
b1111 K
b0 )
b1100101 >
b10000000000 Y
b1000 Q
1[
b1010 U
b10 =
b1001000 :
b1001000 $
b1001000 7
b1001000 L
b0 &
b0 5
b0 J
1h
b1100 S
0m
0]
b0 W
b1001 (
b100000 n
1'
#190000
0'
#200000
0?
0e
b1 @
b1 Y
b1100 Q
0k
0[
b0 U
b1 >
b1010 (
b100000 n
1'
#210000
0'
#220000
b10100 -
b10100 4
b101000000010000000100011 ,
b101000000010000000100011 3
b1100101 b
1l
0f
b1101100 B
1D
1Z
b10000000000 X
b1010 T
b1000000000000 d
b1100 c
b0 ;
b10000 P
b10100 !
b10100 8
b10100 O
b1011 (
b100000 n
1'
#230000
0'
#240000
b11000 -
b11000 4
1?
1e
b1001000 /
1"
b11000 !
b11000 8
b11000 O
1f
b0 B
0D
0Z
b1 X
b0 T
b10000000000 d
b1010 c
b10 ;
b10100 P
bx b
0g
b10000 R
1E
b0 <
b1010 V
1\
b1101100 C
b1100101 :
b1100101 $
b1100101 7
b1100101 L
1m
b1100 (
b100000 n
1'
#250000
0'
#260000
b1 %
b1 6
b1 K
b11011 )
0"
1k
b0 =
b1101100 :
bx $
bx 7
bx L
b1101100 &
b1101100 5
b1101100 J
0h
b10000 S
1]
b1010 W
b1100101 b
1g
b10100 R
0E
b10 <
b0 V
0l
0\
b0 C
b1101 (
b100000 n
1'
#270000
0'
#280000
b1111 %
b1111 6
b1111 K
b0 )
b1101100 @
b10 =
b1100101 :
b1100101 $
b1100101 7
b1100101 L
b0 &
b0 5
b0 J
1h
b10100 S
0m
0]
b0 W
b10000000000 Y
b10000 Q
1[
b1010 U
b1101100 >
b1110 (
b100000 n
1'
#290000
0'
#300000
0?
0e
b1 @
b1 >
b1 Y
b10100 Q
0k
0[
b0 U
b1111 (
b100000 n
1'
#310000
0'
#320000
b11100 -
b11100 4
b110111100000000010110010011 ,
b110111100000000010110010011 3
b11100 !
b11100 8
b11100 O
b11000 P
b1101100 b
1l
b10000 (
b100000 n
1'
#330000
0'
#340000
b100000 -
b100000 4
b101100000010000000100011 ,
b101100000010000000100011 3
b1100101 /
1"
b1101100 :
b1101100 $
b1101100 7
b1101100 L
1m
b11000 R
0f
b1101111 B
1D
1Z
b100000000000 X
b1011 T
b1000000000000000 d
b1111 c
b0 ;
b11100 P
b100000 !
b100000 8
b100000 O
b10001 (
b100000 n
1'
#350000
0'
#360000
b100100 -
b100100 4
b10110000000000011000010011 ,
b10110000000000011000010011 3
1?
1e
b100100 !
b100100 8
b100100 O
1f
b0 B
0D
0Z
b1 X
b0 T
b100000000000 d
b1011 c
b10 ;
b100000 P
bx b
0g
b11100 R
1E
b0 <
b1011 V
1\
b1101111 C
b11000 S
1k
b10010 (
b100000 n
1'
#370000
0'
#380000
b1 %
b1 6
b1 K
b11011 )
0"
b11000 Q
b0 =
b1101111 :
bx $
bx 7
bx L
b1101111 &
b1101111 5
b1101111 J
0h
b11100 S
1]
b1011 W
1g
b100000 R
0E
b10 <
b0 V
0l
0\
b0 C
b10011 (
b100000 n
1'
#390000
0'
#400000
b1111 %
b1111 6
b1111 K
b0 )
b1101111 @
b10 =
bx :
b0 &
b0 5
b0 J
1h
b100000 S
0m
0]
b0 W
b100000000000 Y
b11100 Q
1[
b1011 U
b1101111 >
b10100 (
b100000 n
1'
#410000
0'
#420000
0?
0e
b0x @
b0x >
b1 Y
b100000 Q
0k
0[
b0 U
b10101 (
b100000 n
1'
#430000
0'
#440000
b101000 -
b101000 4
b110000000010000000100011 ,
b110000000010000000100011 3
b101000 !
b101000 8
b101000 O
0f
b101100 B
1D
1Z
b1000000000000 X
b1100 T
b1000000000000 d
b1100 c
b0 ;
b100100 P
b1101111 b
1l
b10110 (
b100000 n
1'
#450000
0'
#460000
b101100 -
b101100 4
b10000000000000011000010011 ,
b10000000000000011000010011 3
b1101100 /
1"
1?
1e
b1101111 :
b1101111 $
b1101111 7
b1101111 L
1m
bx b
0g
b100100 R
1E
b0 <
b1100 V
1\
b101100 C
1f
b0 B
0D
0Z
b1 X
b0 T
b10 ;
b101000 P
b101100 !
b101100 8
b101100 O
b10111 (
b100000 n
1'
#470000
0'
#480000
b1 %
b1 6
b1 K
b1011 )
0"
b1 @
1g
b101000 R
0E
b10 <
b0 V
0l
0\
b0 C
b0 =
b101100 :
bx $
bx 7
bx L
b101100 &
b101100 5
b101100 J
0h
b100100 S
1]
b1100 W
1k
b1 >
b11000 (
b100000 n
1'
#490000
0'
#500000
b101100 @
b1111 %
b1111 6
b1111 K
b0 )
b101100 >
b1000000000000 Y
b100100 Q
1[
b1100 U
b10 =
bx :
b0 &
b0 5
b0 J
1h
b101000 S
0m
0]
b0 W
b11001 (
b100000 n
1'
#510000
0'
#520000
0?
0e
b0x @
b1 Y
b101000 Q
0k
0[
b0 U
b0x >
b11010 (
b100000 n
1'
#530000
0'
#540000
b110000 -
b110000 4
b110000000010000000100011 ,
b110000000010000000100011 3
b101100 b
1l
0f
b100000 B
1D
1Z
b1000000000000 X
b1100 T
b1 d
b0 c
b0 ;
b101100 P
b110000 !
b110000 8
b110000 O
b11011 (
b100000 n
1'
#550000
0'
#560000
b110100 -
b110100 4
b101011100000000011000010011 ,
b101011100000000011000010011 3
1?
1e
b1101111 /
1"
b110100 !
b110100 8
b110100 O
1f
b0 B
0D
0Z
b1 X
b0 T
b1000000000000 d
b1100 c
b10 ;
b110000 P
b0 b
0g
b101100 R
1E
b0 <
b1100 V
1\
b100000 C
b101100 :
b101100 $
b101100 7
b101100 L
1m
b11100 (
b100000 n
1'
#570000
0'
#580000
b1 @
b1 %
b1 6
b1 K
b1000 )
0"
b1 >
1k
b0 =
b100000 :
b0 $
b0 7
b0 L
b100000 &
b100000 5
b100000 J
0h
b101100 S
1]
b1100 W
b101100 b
1g
b110000 R
0E
b10 <
b0 V
0l
0\
b0 C
b11101 (
b100000 n
1'
#590000
0'
#600000
b1111 %
b1111 6
b1111 K
b0 )
b100000 @
b10 =
b101100 :
b101100 $
b101100 7
b101100 L
b0 &
b0 5
b0 J
1h
b110000 S
0m
0]
b0 W
b1000000000000 Y
b101100 Q
1[
b1100 U
b100000 >
b11110 (
b100000 n
1'
#610000
0'
#620000
0?
0e
b1 @
b1 >
b1 Y
b110000 Q
0k
0[
b0 U
b11111 (
b100000 n
1'
#630000
0'
#640000
b111000 -
b111000 4
b110000000010000000100011 ,
b110000000010000000100011 3
b111000 !
b111000 8
b111000 O
0f
b1010111 B
1D
1Z
b1000000000000 X
b1100 T
b100000000000000000000000 d
b10111 c
b0 ;
b110100 P
b100000 b
1l
b100000 (
b100000 n
1'
#650000
0'
#660000
b111100 -
b111100 4
b101100000010000000100011 ,
b101100000010000000100011 3
b101100 /
1"
1?
1e
b100000 :
b100000 $
b100000 7
b100000 L
1m
bx b
0g
b110100 R
1E
b0 <
b1100 V
1\
b1010111 C
1f
b0 B
0D
0Z
b1 X
b0 T
b1000000000000 d
b1100 c
b10 ;
b111000 P
b111100 !
b111100 8
b111100 O
b100001 (
b100000 n
1'
#670000
0'
#680000
b1 %
b1 6
b1 K
b10101 )
0"
b100000 b
1g
b111000 R
0E
b10 <
b0 V
0l
0\
b0 C
b0 =
b1010111 :
bx $
bx 7
bx L
b1010111 &
b1010111 5
b1010111 J
0h
b110100 S
1]
b1100 W
1k
b100010 (
b100000 n
1'
#690000
0'
#700000
b1010111 @
b1111 %
b1111 6
b1111 K
b0 )
b1010111 >
b1000000000000 Y
b110100 Q
1[
b1100 U
b10 =
b100000 :
b100000 $
b100000 7
b100000 L
b0 &
b0 5
b0 J
1h
b111000 S
0m
0]
b0 W
b100011 (
b100000 n
1'
#710000
0'
#720000
0?
0e
b1 @
b1 Y
b111000 Q
0k
0[
b0 U
b1 >
b100100 (
b100000 n
1'
#730000
0'
#740000
b1000000 -
b1000000 4
b111001000000000010110010011 ,
b111001000000000010110010011 3
b1010111 b
1l
b100000000000 d
b1011 c
b111100 P
b1000000 !
b1000000 8
b1000000 O
b100101 (
b100000 n
1'
#750000
0'
#760000
b1000100 -
b1000100 4
b101100000010000000100011 ,
b101100000010000000100011 3
b100000 /
1"
b1000100 !
b1000100 8
b1000100 O
0f
b1110010 B
1D
1Z
b100000000000 X
b1011 T
b1000000000000000000 d
b10010 c
b0 ;
b1000000 P
b1101111 b
b111100 R
b1010111 :
b1010111 $
b1010111 7
b1010111 L
1m
b100110 (
b100000 n
1'
#770000
0'
#780000
b1001000 -
b1001000 4
b101000000010000000100011 ,
b101000000010000000100011 3
b1010111 /
1?
1e
1k
b1101111 :
b1101111 $
b1101111 7
b1101111 L
b111100 S
bx b
0g
b1000000 R
1E
b0 <
b1011 V
1\
b1110010 C
1f
b0 B
0D
0Z
b1 X
b0 T
b100000000000 d
b1011 c
b10 ;
b1000100 P
b1001000 !
b1001000 8
b1001000 O
b100111 (
b100000 n
1'
#790000
0'
#800000
b1 %
b1 6
b1 K
b11100 )
0"
b1101111 b
1g
b1000100 R
0E
b10 <
b0 V
0l
0\
b0 C
b0 =
b1110010 :
bx $
bx 7
bx L
b1110010 &
b1110010 5
b1110010 J
0h
b1000000 S
1]
b1011 W
b111100 Q
b101000 (
b100000 n
1'
#810000
0'
