risac.v
module risac (
  input						clk, rst_n,
  output	[31:0] 	oIbusAddr,
  input		[31:0] 	iIbusData,
  input		[31:0]	iIbusIAddr,
  input						iIbusWait,
  output          oIbusRead,
  
  output	[31:0]	oDbusAddr,
  output					oDbusWe,
  output	[31:0]	oDbusData,
  output					oDbusRead,
  output	[3:0]		oDbusByteEn,
  input		[31:0]	iDbusData,
  input						iDbusWait
);

  // ===========================================================
  // the instruction address generation logic
  // pc contains the byte address
  reg [31:0] pc;
  reg [31:0] branchTarget;
  reg branch;
  reg dataHazard;
  reg stallPipe;
  reg pcChanged;
  
  assign oIbusAddr = pc;
  // wait for waitrequest to fall before zeroing
  // read (i.e.) wait till a pending request is completed
  assign oIbusRead = iIbusWait ? 1'b1 : pcChanged;

  always @ (posedge clk or negedge rst_n) begin: IF
    if (!rst_n) begin 
      pc <= 'b0;
      pcChanged <= 'b1;
    end	else if (!stallPipe && !dataHazard | branch) begin 
      // new data arrives when wait is 0
      // so update pc when wait is 0
      pc <= iIbusWait ? pc : (branch ? branchTarget : pc + 3'd4);

      // assert read regardless of wait
      // but only when pc is updated
      // also dont deassert when wait is high
      // pcChanged <= iIbusWait ? 1'b0 : 1'b1;
      if (!iIbusWait) begin 
        pcChanged <= 1'b1;
      end else begin 
        pcChanged <= 1'b0;
      end
    end else begin
      pcChanged <= 1'b0;
    end
  end

  // ===========================================================
  // decode the instruction 
  // for now support only rtype, itype and stype

  reg [3:0]		aluOpDec;
  reg [4:0]		rs1Dec, rs2Dec, rdDec;
  reg [31:0]	immDec, pcDec, rs1ShiftDec, rs2ShiftDec, rdShiftDec;
  reg 				validDec;
  reg					immSelDec;
  reg 				rdWeDec;
  reg					illegalDec;
  reg					lDec, sDec, luipcDec, luiDec;
  reg         branchDec;
  reg         branchType;
  reg					jalr;

  always @ (posedge clk or negedge rst_n) begin: DEC
    if (!rst_n) begin 
      {aluOpDec, rs1Dec, rs2Dec, immDec, validDec, immSelDec, rdShiftDec} <= 'b0;
      {rdWeDec, illegalDec, pcDec, lDec, sDec, rs1ShiftDec, rs2ShiftDec} <= 'b0; 
      {luipcDec, luiDec, branchDec, branchType, jalr} <= 'b0;
    end else if (!stallPipe && !dataHazard) begin 
      // the address of the currently being decoded instruction
      pcDec			<= iIbusIAddr;

      // the instruction is valid if there is not wait signal
      validDec	<= ~iIbusWait;

      // decode the instruction regardless of validity

      // branch instructions
      // only branch opcodes begin with 110
      branchDec   <= iIbusData[6:4] == 3'b110;
      // for conditional branches, the next 2 bits are zero
      // branchType: zero for unconditional, 1 for conditional
      // for all branches, pc <= pc + offset
      // except jalr, pc <= rs1 + offset 
      branchType  <= iIbusData[3:2] == 2'b00;
      jalr <= iIbusData[3:2] == 2'b01;

      // lui and auipc are special
      luipcDec <= iIbusData[4:2] == 3'b101;
      luiDec   <= iIbusData[5:2] == 4'b1101;

      // alu op is always [14:12]
      aluOpDec[2:0]	<= iIbusData[14:12];
      aluOpDec[3]		<= iIbusData[30];

      // rs1, rs2 and rd are fixed
      rs1Dec			<= iIbusData[19:15];
      rs2Dec			<= iIbusData[24:20];
      rs1ShiftDec	<= 1 << iIbusData[19:15];
      rs2ShiftDec <= 1 << iIbusData[24:20];
      rdDec				<= iIbusData[11:7];
      rdShiftDec 	<= 1 << iIbusData[11:7];

      // always write to rd except when storing or conditional branching
      // all instructions except stores and conditional branches have 4:2 
      // not equal to zero
      rdWeDec		<= (iIbusData[4:2] != 3'b000);
      
      // select imm when instr[6:4] == 001
      // in rv32i, no other instruction has opcode[6:4] == 001 other than those
      // that use imm
      // lui also uses imm
      // jalr and jal also use imm
      immSelDec	<=  (iIbusData[6:4] == 3'b001) | 
                    (iIbusData[6:2] == 5'b01101) | 
                    (iIbusData[6:2] == 5'b11011) |
                    (iIbusData[6:2] == 5'b11001);

      // for the imm, use the opcode
      case (iIbusData[6:2]) // the last 2 bits are always 1 anyway
      
      // itype load
      5'b00000: immDec <= { {21{iIbusData[31]}}, iIbusData[30:20] };
      // itype alu
      5'b00100: immDec <= { {21{iIbusData[31]}}, iIbusData[30:20] };
      // jalr
      5'b11001: immDec <= { {21{iIbusData[31]}}, iIbusData[30:20] };
      
      // SType: store
      5'b01000: immDec <= { {21{iIbusData[31]}}, iIbusData[30:25], iIbusData[11:7] };

      // lui
      5'b01101: immDec <= { iIbusData[31:12], 12'b0 };
      // auipc
      5'b00101: immDec <= { iIbusData[31:12], 12'b0 };
      // jal
      5'b11011: immDec <= { {12{iIbusData[31]}}, iIbusData[19:12], iIbusData[20], iIbusData[30:25], iIbusData[24:21], 1'b0 };

      // btype, all conditional branches
      5'b11000: immDec <= { {20{iIbusData[31]}}, iIbusData[7], iIbusData[30:25], iIbusData[11:8], 1'b0 };

      endcase

      // load when all zero opcode
      lDec <= iIbusData[6:2] == 5'b00000;
      sDec <= iIbusData[6:2] == 5'b01000;

      // for now ignore the illegal instruction
      // TODO: add illegal indication
    end
  end

  // ===========================================================
  // fetch the operands from the register file
  // the register file has registered outputs

  // also maintain a RAT to track which registers are dirty
  // if dirty registers are needed, stall the previous stages
  // till clean value arrives and invalidate all the instructions
  // that are sent forward 

  reg [31:0]	registers [0:31];
  reg [31:0]	rs1Data, rs2Data, rdShiftEx;
  
  // data hazard handling mech
  reg [31:0]  rat [0:1];
  reg 				stallDataHazard;
  reg         falseAlarm;
  reg [1:0]   sourceEqual;

  reg 				validEx, rdWeEx;
	reg [2:0]   invalidRegister;

  integer idx;

  always @ (posedge clk or negedge rst_n) begin: RAT
    if (!rst_n) begin 
      rat[0] <= 'b0;
      rat[1] <= 'b0;
      falseAlarm <= 'b0;
      sourceEqual <= 'b0;
    end else if (!stallPipe) begin
      // update rat
      // set rd'th bit to 1 in rat[0..1]
      // if it is 1 then set it 1 anyway
      // set the rdEx'th bit to 0 in rat[0..1]
      // setting 1 takes priority

      // the zero register is always clean
      rat[0][0] <= 1'b0;
      rat[1][0] <= 1'b0;

      // on the condition that if rat[rd] is already 1 then 
      // 1. add x2, x1, x3
      // 2. add x2, x2, x4
      // when 1 is written back, rat[2] is set to 1 instead of 0
      // because 2 will force it
      // in this case, we must allow only 1 instruction to pass
      // we use a false alarm bit for this

      // raise false alarm when rdDec == rdEx and all the valid conditions
      // also set false alarm to zero if it is one
      if (falseAlarm) begin 
        falseAlarm <= 'b0;
        sourceEqual<= 'b0;
      end else if (rdWeDec && validDec && rdWeEx && validEx) begin 
        falseAlarm <= rdEx == rdDec;
        sourceEqual<= {(rs1Dec == rdEx), (rs2Dec == rdDec)};
      end

      for (idx = 1; idx < 32; idx = idx + 1) begin
        // there is also a false alarm when after a branch instruction is decoded,
        // another instruction sets the rat which is invalidated after the branch is taken
        // but the rat remains there and is not fixed

        // the code below fixes this by zeroing the rat set by the instructions currently in
        // of and dec
        if (branch) begin 
          if (rdOf == idx && validOf && rdWeOf) begin 
            // the possible instructions that set the rat are now in of
            // the instruction in dec can set the rat
            rat[0][idx] <= 1'b0;
            rat[1][idx] <= 1'b0;
          end 
          else if (rdDec == idx && validDec && rdWeDec) begin 
            rat[0][idx] <= 1'b0;
            rat[1][idx] <= 1'b0;
          end
        end 
        // if the register to be updated [(rdDecWe == 1) and (rdShiftDec[idx] == 1)]
        // then set the rat to 1 
        else if (rdWeDec && rdShiftDec[idx] && validDec && !dataHazard && !(|invalidRegister[1:0])) begin 
          rat[0][idx] <= 1'b1;
          rat[1][idx] <= 1'b1;
        end
        // else if the register is *being* updated [(rdExWe == 1) and (rdShiftEx[idx] == 1)]
        // then set the rat to 0
        else if (rdWeEx && rdShiftEx[idx] && validEx) begin 
          rat[0][idx] <= 1'b0;
          rat[1][idx] <= 1'b0;
        end			
      end
    end
  end

  // combinational part 
  reg rs1booked;
  reg rs2booked;
  always @ (*) begin: DATA_HAZARD_DETECTION
    // check if rs1 and rs2 are 'booked'
    // TODO: maybe take a look at this again
    // rs1 is booked if rat[0] is set and the instruction is not
    // lui, auipc
    rs1booked = |(rs1ShiftDec & rat[0]) && ~luipcDec;
    // rs2 is booked if rat[1] is set and the instruction is not 
    // one that uses imm
    rs2booked = |(rs2ShiftDec & rat[1]) && ~immSelDec;

    
    // data hazard occurs when rs1 or rs2 is booked and nothing is being written
    // to the regfile 
    // if there is data being written to the reg file then no need to stall, let it
    // pass
    dataHazard = falseAlarm ? (rs1booked & sourceEqual[1]) | (rs2booked & sourceEqual[0]) : ((rs1booked) | (rs2booked));
  end
  
  // when the data hazard occurs, set valid to zero and stall previous stages

  // propogate the rdWe, valid, aluOp, immSel, pc and imm signals
  reg					validOf, rdWeOf, immSelOf;	
  reg [31:0]	immOf, pcOf;
  reg [3:0]		aluOpOf;
  reg [4:0]		rdOf;
  reg 				lOf, sOf, luipcOf;
  reg         branchOf, compareOf;
  reg [31:0]	bTargetOf, branchOffset;

  always @ (posedge clk or negedge rst_n) begin: OF
    if (!rst_n) begin 
      {rs1Data, rs2Data, validOf, rdWeOf, immOf} <= 'b0;
      {pcOf, immSelOf, aluOpOf, rdOf, lOf, sOf, luipcOf, branchOf} <= 'b0;
      {compareOf, bTargetOf, branchOffset} <= 'b0;
      // !do not reset the registers!!

    end else if (!stallPipe) begin 
      // propogation
      {rdWeOf} <= {rdWeDec};
      {immSelOf, rdOf} <= {immSelDec, rdDec};
      {lOf, sOf, luipcOf} <= {lDec, sDec, luipcDec};

      // branch handles
      // branchOf signal is high when the branch is unconditional
      // e.g. jal, jalr
      branchOf <= branchDec & ~branchType;
      // compareOf is high when the branch is a conditional branch
      // e.g. bne, ...
      compareOf<= branchDec & branchType;
      
      bTargetOf<= jalr ? (rs1Dec == 5'b0 ? 32'b0 : registers [rs1Dec]) : pcDec;
      branchOffset <= immDec;

      if (falseAlarm) begin 
        validOf <= validDec;
      end else begin 
        validOf <= validDec & ~dataHazard;
      end 

      rs1Data <= rs1Dec == 5'b0 ? 32'b0 : registers [rs1Dec];
      rs2Data	<= rs2Dec == 5'b0 ? 32'b0 : registers [rs2Dec];
      aluOpOf <= luipcDec | (branchDec & ~branchType) ? 4'b0 : aluOpDec;
      pcOf    <= luiDec ? 32'b0 : pcDec;
      immOf   <= (branchDec & ~branchType) ? 32'd4 : immDec;
    end
  end

  // ============================================================
  // select the operands to feed the alu and lsu
  // add the imm in rs1 to get the address
  // the data to store is in rs2


  reg [31:0] 	aluIn1, aluIn2;

  // propogate the valid, aluOp, rdWe, pc
  reg [31:0] 	pcOs;
  reg [3:0]		aluOpOs;
  reg 				validOs, rdWeOs;
  reg [4:0]		rdOs;
  reg 				lOs, sOs;
  reg [31:0]	lsuAddrOs, lsuDataOs;
  
  // the branch compare signals
	reg					compareResult;
	
	
	// the branch comparators
	always @ (*) begin: BRANCH_COMPARATOR
    case (aluOpOf[2:0])
    3'b000: 	compareResult = rs1Data == rs2Data;
    3'b001: 	compareResult = rs1Data != rs2Data;
    3'b100: 	compareResult = $signed(rs1Data) <  $signed(rs2Data);
    3'b101: 	compareResult = $signed(rs1Data) >= $signed(rs2Data);
    3'b110: 	compareResult = rs1Data <  rs2Data;
    3'b111: 	compareResult = rs1Data >= rs2Data;
    default: compareResult = 1'b0;
    endcase
  end
	
	// the branch hazard handling technique
	// invalidate 3 instructions if the branch
	// is taken
	
	
	always @ (posedge clk or negedge rst_n) begin: BRANCH_HANDLER
    if (!rst_n) begin 
      invalidRegister <= 'b0;
    end else if (!stallPipe) begin 
      invalidRegister[0] <= ((compareResult & compareOf) | branchOf) & validOf;
      invalidRegister[1] <= invalidRegister[0];
      invalidRegister[2] <= invalidRegister[1];
    end
  end
	
  always @ (posedge clk or negedge rst_n) begin: OS
    if (!rst_n) begin 
      {pcOs, aluOpOs, validOs, rdWeOs, rdOs} <= 'b0;
      {aluIn1, aluIn2, lOs, sOs, lsuAddrOs, lsuDataOs} <= 'b0;
      {branch, branchTarget} <= 'b0;
    end else if (!stallPipe) begin 
      {pcOs, rdWeOs, rdOs} <= {pcOf, rdWeOf, rdOf};
      {lOs, sOs} <= {lOf, sOf};

      // the branch unit
      // branch only if instruction was unconditional branch
      // and if it was conditional then branch if the condition met

      branch <= (branchOf | (compareResult & compareOf)) & validOf;
			branchTarget <= bTargetOf + branchOffset;
			validOs <= (|invalidRegister) ? 1'b0 : validOf;

      lsuAddrOs <= rs1Data + immOf;
      lsuDataOs <= rs2Data;

      // when lui comes, the imm is the value 
      // so zero aluIn1 and set operation to add
      aluIn1	<= (luipcOf | branchOf) ? pcOf : rs1Data;

      // aluIn2 is between imm and rs2Data
      aluIn2	<= immSelOf ? immOf : rs2Data;

      // if IType and the operation is add then clear op[3],
      // coz there is no subi 
      if (immSelOf && (aluOpOf[2:0] == 3'b000))
        aluOpOs[3] <= 1'b0;
      else 
        aluOpOs[3] <= aluOpOf[3];

      aluOpOs[2:0] <= aluOpOf[2:0]; 
    end
  end

  // ============================================================
  // the execute stage
  // can have multiple units in paralell
  // for now we only have the alu and lsu 
  reg [31:0] exRes;

  // propogate the valid, pc, rdWe
  reg [31:0]	pcEx;
  reg [4:0]		rdEx;

  always @ (posedge clk or negedge rst_n) begin: EX
    if (!rst_n) begin 
      {pcEx, validEx, rdWeEx, rdEx, rdShiftEx} <= 'b0;
    end else if (!stallPipe) begin
      {pcEx, validEx, rdWeEx, rdEx} <= {pcOs, validOs, rdWeOs, rdOs};
      rdShiftEx <= 1 << rdOs;			
    end
  end

  // ============================================================
  // the alu has a fixed latency of 1
  // the alu causes no stalls
  reg [31:0]	aluRes;

  always @ (posedge clk or negedge rst_n) begin: EX_ALU
    if (!rst_n) begin 
      aluRes <= 'b0;
    end else begin 
      case (aluOpOs[2:0])
      3'b000: aluRes <= aluOpOs[3] ? aluIn1 - aluIn2 : aluIn1 + aluIn2;	// add/sub
      3'b001: aluRes <= aluIn1 << aluIn2[4:0];	// sll
      3'b010: aluRes <= $signed(aluIn1) < $signed(aluIn2) ? 32'b1 : 32'b0; 
      3'b011: aluRes <= aluIn1 < aluIn2 ? 32'b1 : 32'b0;
      3'b100: aluRes <= aluIn1 ^ aluIn2;
      3'b101: aluRes <= aluOpOs[3] ? $signed($signed(aluIn1) >>> aluIn2[4:0]) : aluIn1 >> aluIn2[4:0];
      3'b110: aluRes <= aluIn1 | aluIn2;
      3'b111: aluRes <= aluIn1 & aluIn2;
      endcase
    end 
  end

  // ============================================================
  // the lsu has min latency of 1 
  // max latency of infinity
  // lsu can stall the pipeline 
  // data to store in rs2

  reg [31:0]	lsuRes;
  reg 				lsuStall;
  reg [3:0]		lsuByteEn;
  reg 				lEx;

  assign oDbusAddr 		= lsuAddrOs;
  assign oDbusRead 		= lOs & validOs;
  assign oDbusWe	 		= sOs & validOs;
  assign oDbusData 		= lsuDataOs;
  assign oDbusByteEn 	= lsuByteEn;

  // wait only asserted when reading, writing does not assert wait
  // from m4k, reads have min latency of 1

  always @ (*) begin: EX_LSU_BYTEENABLE_GENERATOR
    lsuStall = iDbusWait & (lOs | sOs) & validOs;
  
    case (aluOpOs[1:0]) 
    2'b00:	lsuByteEn = 4'b1;			// sb/lb
    2'b01:	lsuByteEn = 4'b11;		// sh/lh
    2'b10:	lsuByteEn	= 4'b1111;	// sw/lw
    default:lsuByteEn = 4'b0;	
    endcase
  end

  always @ (posedge clk or negedge rst_n) begin: EX_LSU
    if (!rst_n) begin 
      lsuRes 	<= 'b0;
      lEx 		<= 'b0;
    end	else if (!stallPipe) begin 
      lEx 		<= lOs;
      if (aluOpOs[1]) begin  // lw
        lsuRes <= iDbusData;
      end else begin 
        case ({aluOpOs[2], aluOpOs[0]}) 
        2'b00: lsuRes <= { {24{iDbusData[07]}}, iDbusData[07:0] };	// lb
        2'b01: lsuRes <= { {16{iDbusData[15]}}, iDbusData[15:0] };	// lh
        2'b10: lsuRes <= { 24'b0, iDbusData[07:0] };	// lbu
        2'b11: lsuRes <= { 16'b0, iDbusData[15:0] };	// lhu 
        endcase
      end
    end
  end

  // ============================================================
  // the stall handling mech,
  // simply or the stalls from all the sources
  // for now, only lsu can stall
  // IF doesn't stall, it keeps sending invalid instructions
  // which don't affect anything

  always @ (*) begin: EX_LSU_STALL_GENERATOR
    stallPipe = lsuStall;
  end	

  // ============================================================
  // the write back stage

  // mux the result from various stages
  // for now, if load instruction, then select lsuRes
  always @ (*) begin: WB_MUX
    exRes	= lEx ? lsuRes : aluRes;
  end

  always @ (posedge clk) begin: WB_REGISTER_FILE
    // do not reset the register file
    // write back if valid only
    if (validEx && rdWeEx) begin 
      registers[rdEx] <= exRes;
    end
  end
endmodule

testbench/risac_tb_single_mem.v
`timescale 1ns / 1ps

module testbench();

  reg						clk = 1, rst_n = 0;
  wire	[31:0] 	oIbusAddr;
  reg		[31:0] 	iIbusData;
  reg		[31:0]	iIbusIAddr;
  reg						iIbusWait;
  
  wire	[31:0]	oDbusAddr;
  wire					oDbusWe;
  wire	[31:0]	oDbusData;
  wire					oDbusRead;
  wire	[3:0]		oDbusByteEn;
  reg		[31:0]	iDbusData;
  reg						iDbusWait;

  wire  [31:0]  rat0, rat1;

  risac u_risac (
    .clk          (clk),
    .rst_n        (rst_n),

    // The IBUS

    .oIbusAddr    (oIbusAddr),
    .iIbusData    (iIbusData),
    .iIbusIAddr   (iIbusIAddr),
    .iIbusWait    (iIbusWait),
    
    // The DBUS

    .oDbusAddr    (oDbusAddr),
    .oDbusWe      (oDbusWe),
    .oDbusData    (oDbusData),
    .oDbusRead    (oDbusRead),
    .oDbusByteEn  (oDbusByteEn),
    .iDbusData    (iDbusData),
    .iDbusWait    (iDbusWait)
  );

  assign rat0 = u_risac.rat[0];
  assign rat1 = u_risac.rat[1];

  reg [7:0] mem [0:4095]; // 4K ram
  reg [31:0] cnt = 0;

  // create a clock
  always @ (posedge clk) begin 
    cnt = cnt + 1;
  end

  always begin 
    #10 
    clk = !clk;
  end

  // initialize the memories
  integer i;
  initial begin 
    // prepare a vcd dump
    $dumpfile("risac2.vcd");
    $dumpvars(0, testbench);
    $readmemh("program.vh", mem);

    $display ("\n======================");
    $display ("RISCV Virtual Terminal");
    $display ("======================\n"); 
    
    #5
    rst_n = 1'b1;



    #5000 
    // dump memory to output 
    $display ("======================\n"); 
    
    $finish;
  end

  // create a memory system
  // simple zero latency memory

  // ==========================
  // the instruction bus
  // ==========================

  always @ (oIbusAddr) begin 
    iIbusWait <= 1'b0;
    iIbusData <= {mem [oIbusAddr+3], mem [oIbusAddr+2], mem [oIbusAddr+1], mem [oIbusAddr]};
    iIbusIAddr<= oIbusAddr;
  end


  reg [7:0]  dmem_addr;
  reg [31:0] and_mask;

  always @ (cnt) begin 
    // the virtual console 
    if (oDbusWe && oDbusAddr == 32'h10000 && oDbusByteEn[0]) begin 
      $write("%c", oDbusData[7:0]);		
    end
  end 

  reg [31:0] oldWord;

  always @ (*) begin 
    iDbusData = 'b0;
    iDbusWait = 'b0;
    
    if (oDbusWe) begin 
      mem[oDbusAddr]     = oDbusByteEn[0] ? oDbusData[07:00] : mem[oDbusAddr];
      mem[oDbusAddr + 1] = oDbusByteEn[1] ? oDbusData[15:08] : mem[oDbusAddr + 1];
      mem[oDbusAddr + 2] = oDbusByteEn[2] ? oDbusData[23:16] : mem[oDbusAddr + 2];
      mem[oDbusAddr + 3] = oDbusByteEn[3] ? oDbusData[31:24] : mem[oDbusAddr + 3];
    end
    
    if (oDbusRead) begin 
      iDbusData = {mem[oDbusAddr + 3], mem[oDbusAddr + 2], mem[oDbusAddr + 1], mem[oDbusAddr]};
    end
  end

endmodule

testbench/risac.vcd
$date
	Mon Nov 25 22:39:20 2019
$end
$version
	Icarus Verilog
$end
$timescale
	1ps
$end
$scope module testbench $end
$var wire 32 ! rat0 [31:0] $end
$var wire 32 " rat1 [31:0] $end
$var wire 32 # oIbusAddr [31:0] $end
$var wire 1 $ oDbusWe $end
$var wire 1 % oDbusRead $end
$var wire 32 & oDbusData [31:0] $end
$var wire 4 ' oDbusByteEn [3:0] $end
$var wire 32 ( oDbusAddr [31:0] $end
$var reg 1 ) clk $end
$var reg 32 * cnt [31:0] $end
$var reg 8 + dmem_addr [7:0] $end
$var reg 32 , iDbusData [31:0] $end
$var reg 1 - iDbusWait $end
$var reg 32 . iIbusData [31:0] $end
$var reg 32 / iIbusIAddr [31:0] $end
$var reg 1 0 iIbusWait $end
$var reg 32 1 oldWord [31:0] $end
$var reg 1 2 rst_n $end
$var integer 32 3 i [31:0] $end
$scope module u_risac $end
$var wire 1 ) clk $end
$var wire 32 4 iDbusData [31:0] $end
$var wire 1 - iDbusWait $end
$var wire 32 5 iIbusData [31:0] $end
$var wire 32 6 iIbusIAddr [31:0] $end
$var wire 1 0 iIbusWait $end
$var wire 32 7 oDbusAddr [31:0] $end
$var wire 4 8 oDbusByteEn [3:0] $end
$var wire 32 9 oDbusData [31:0] $end
$var wire 1 % oDbusRead $end
$var wire 1 $ oDbusWe $end
$var wire 32 : oIbusAddr [31:0] $end
$var wire 1 2 rst_n $end
$var wire 1 ; oIbusRead $end
$var reg 32 < aluIn1 [31:0] $end
$var reg 32 = aluIn2 [31:0] $end
$var reg 4 > aluOpDec [3:0] $end
$var reg 4 ? aluOpOf [3:0] $end
$var reg 4 @ aluOpOs [3:0] $end
$var reg 32 A aluRes [31:0] $end
$var reg 32 B bTargetOf [31:0] $end
$var reg 1 C branch $end
$var reg 1 D branchDec $end
$var reg 1 E branchOf $end
$var reg 32 F branchOffset [31:0] $end
$var reg 32 G branchTarget [31:0] $end
$var reg 1 H branchType $end
$var reg 1 I compareOf $end
$var reg 1 J compareResult $end
$var reg 1 K dataHazard $end
$var reg 32 L exRes [31:0] $end
$var reg 1 M falseAlarm $end
$var reg 1 N illegalDec $end
$var reg 32 O immDec [31:0] $end
$var reg 32 P immOf [31:0] $end
$var reg 1 Q immSelDec $end
$var reg 1 R immSelOf $end
$var reg 3 S invalidRegister [2:0] $end
$var reg 1 T jalr $end
$var reg 1 U lDec $end
$var reg 1 V lEx $end
$var reg 1 W lOf $end
$var reg 1 X lOs $end
$var reg 32 Y lsuAddrOs [31:0] $end
$var reg 4 Z lsuByteEn [3:0] $end
$var reg 32 [ lsuDataOs [31:0] $end
$var reg 32 \ lsuRes [31:0] $end
$var reg 1 ] lsuStall $end
$var reg 1 ^ luiDec $end
$var reg 1 _ luipcDec $end
$var reg 1 ` luipcOf $end
$var reg 32 a pc [31:0] $end
$var reg 1 b pcChanged $end
$var reg 32 c pcDec [31:0] $end
$var reg 32 d pcEx [31:0] $end
$var reg 32 e pcOf [31:0] $end
$var reg 32 f pcOs [31:0] $end
$var reg 5 g rdDec [4:0] $end
$var reg 5 h rdEx [4:0] $end
$var reg 5 i rdOf [4:0] $end
$var reg 5 j rdOs [4:0] $end
$var reg 32 k rdShiftDec [31:0] $end
$var reg 32 l rdShiftEx [31:0] $end
$var reg 1 m rdWeDec $end
$var reg 1 n rdWeEx $end
$var reg 1 o rdWeOf $end
$var reg 1 p rdWeOs $end
$var reg 32 q rs1Data [31:0] $end
$var reg 5 r rs1Dec [4:0] $end
$var reg 32 s rs1ShiftDec [31:0] $end
$var reg 1 t rs1booked $end
$var reg 32 u rs2Data [31:0] $end
$var reg 5 v rs2Dec [4:0] $end
$var reg 32 w rs2ShiftDec [31:0] $end
$var reg 1 x rs2booked $end
$var reg 1 y sDec $end
$var reg 1 z sOf $end
$var reg 1 { sOs $end
$var reg 2 | sourceEqual [1:0] $end
$var reg 1 } stallPipe $end
$var reg 1 ~ validDec $end
$var reg 1 !" validEx $end
$var reg 1 "" validOf $end
$var reg 1 #" validOs $end
$var integer 32 $" idx [31:0] $end
$scope begin BRANCH_COMPARATOR $end
$upscope $end
$scope begin BRANCH_HANDLER $end
$upscope $end
$scope begin DATA_HAZARD_DETECTION $end
$upscope $end
$scope begin DEC $end
$upscope $end
$scope begin EX $end
$upscope $end
$scope begin EX_ALU $end
$upscope $end
$scope begin EX_LSU $end
$upscope $end
$scope begin EX_LSU_BYTEENABLE_GENERATOR $end
$upscope $end
$scope begin EX_LSU_STALL_GENERATOR $end
$upscope $end
$scope begin IF $end
$upscope $end
$scope begin OF $end
$upscope $end
$scope begin OS $end
$upscope $end
$scope begin RAT $end
$upscope $end
$scope begin WB_MUX $end
$upscope $end
$scope begin WB_REGISTER_FILE $end
$upscope $end
$upscope $end
$upscope $end
$enddefinitions $end
#0
$dumpvars
bx $"
0#"
0""
0!"
0~
0}
b0 |
0{
0z
0y
0x
b0 w
b0 v
b0 u
0t
b0 s
b0 r
b0 q
0p
0o
0n
0m
b0 l
b0 k
b0 j
b0 i
b0 h
bx g
b0 f
b0 e
b0 d
b0 c
1b
b0 a
0`
0_
0^
0]
b0 \
b0 [
b1 Z
b0 Y
0X
0W
0V
0U
0T
b0 S
0R
0Q
b0 P
b0 O
0N
0M
b0 L
0K
1J
0I
0H
b0 G
b0 F
0E
0D
0C
b0 B
b0 A
b0 @
b0 ?
b0 >
b0 =
b0 <
1;
b0 :
b0 9
b1 8
b0 7
b0 6
b10100010011 5
b0 4
bx 3
02
bx 1
00
b0 /
b10100010011 .
0-
b0 ,
b0 +
b0 *
1)
b0 (
b1 '
b0 &
0%
0$
b0 #
b0 "
b0 !
$end
#5000
12
#10000
0)
#20000
b100 /
b100 6
b111010110111101010110110111 .
b111010110111101010110110111 5
b1 l
bx i
1Q
1m
b10000000000 k
b1010 g
b1 w
b1 s
1H
1~
b100 #
b100 :
b100 a
b1 *
b100000 $"
1)
#30000
0)
#40000
b1000 /
b1000 6
b11010001010101011000011110010011 .
b11010001010101011000011110010011 5
bx j
1""
1R
b1010 i
1o
b10000000000 "
b10000000000 !
b111010110111101000000000000 O
b100000000000 k
b1011 g
b1000000000000000000000 w
b100000000000000000000000 s
b10101 v
b10111 r
b101 >
1^
1_
1T
0H
b100 c
b1000 #
b1000 :
b1000 a
b10 *
b100000 $"
1)
#50000
0)
#60000
b1100 /
b1100 6
b10101100110100101010110110111 .
b10101100110100101010110110111 5
xJ
1K
1t
bx l
bx h
1#"
1p
b1010 j
b111010110111101000000000000 P
bx u
bx q
b111010110111101000000000000 F
bx B
1`
b1011 i
b110000000000 "
b110000000000 !
b11111111111111111111110100010101 O
b1000000000000000 k
b1111 g
b100000000000 s
b1011 r
b1000 >
0^
0_
0T
1H
b1000 c
b1100 #
b1100 :
b1100 a
b11 *
b100000 $"
1)
#70000
0)
#80000
bx +
0;
b10000000000 l
1!"
1n
b1010 h
b111010110111101000000000000 =
bx &
bx 9
bx [
bx (
bx 7
bx Y
bx G
b1011 j
b11111111111111111111110100010101 P
b1000 e
b1000 ?
0""
b11111111111111111111110100010101 F
b1000 B
0`
b1111 i
0b
b100 *
b100000 $"
1)
#90000
0)
#100000
b111010110111101000000000000 L
b111010110111101000000000000 A
b100000000000 l
b1011 h
b11111111111111111111110100010101 =
bx <
0#"
b11111111111111111111110100011101 G
b1000 f
b1111 j
b100000000000 "
b100000000000 !
b101 *
b100000 $"
1)
#110000
0)
#120000
bx L
0K
0t
bx A
b1000000000000000 l
b1000 d
0!"
b1111 h
b0 "
b0 !
b10 |
b110 *
b100000 $"
1)
#130000
0)
#140000
b10000 /
b10000 6
b1011110010101011000010110010011 .
b1011110010101011000010110010011 5
1;
b111010110111101000000000000 q
1""
b1000000000000000 "
b1000000000000000 !
b10101100110100101000000000000 O
b100000000000 k
b1011 g
b10000000000000000000000000 w
b100000000000000000000 s
b11001 v
b10100 r
b101 >
1^
1_
1T
0H
b1100 c
1b
b10000 #
b10000 :
b10000 a
b111 *
b100000 $"
1)
#150000
0)
#160000
b10100 /
b10100 6
b11111000100100100011000110111 .
b11111000100100100011000110111 5
b1000101 +
1K
1t
b111010110111101000000000000 <
b111010110111100110100010101 (
b111010110111100110100010101 7
b111010110111100110100010101 Y
1#"
b10101100110100101000000000000 P
b0 e
b0 ?
bx q
b10101100110100101000000000000 F
bx B
1`
b1011 i
b1000100000000000 "
b1000100000000000 !
b10111100101 O
b100000 w
b100000000000 s
b101 v
b1011 r
b1000 >
0^
0_
0T
1H
b10000 c
b10100 #
b10100 :
b10100 a
b1000 *
b100000 $"
1)
#170000
0)
#180000
b111010110111100110100010101 L
bx +
0;
b111010110111100110100010101 A
1!"
b10101100110100101000000000000 =
b0 <
bx (
bx 7
bx Y
bx G
b0 f
b1011 j
b10111100101 P
b10000 e
b1000 ?
b111010110111101000000000000 q
0""
b10111100101 F
b10000 B
0`
0b
b1001 *
b100000 $"
1)
#190000
0)
#200000
b10101100110100101000000000000 L
b1111001 +
b10101100110100101000000000000 A
b100000000000 l
b0 d
b1011 h
b10111100101 =
b111010110111101000000000000 <
b111010110111101010111100101 (
b111010110111101010111100101 7
b111010110111101010111100101 Y
0#"
b10111110101 G
b10000 f
b100000000000 "
b100000000000 !
b0 |
b1010 *
b100000 $"
1)
#210000
0)
#220000
b111010110111101010111100101 L
0K
0t
b111010110111101010111100101 A
b10000 d
0!"
b0 "
b0 !
b10 |
1M
b1011 *
b100000 $"
1)
#230000
0)
#240000
b11000 /
b11000 6
b10111011010101100000011000010011 .
b10111011010101100000011000010011 5
1;
b10101100110100101000000000000 q
1""
b100000000000 "
b100000000000 !
b0 |
0M
b11111000100100100000000000000 O
b1000000000000 k
b1100 g
b100000000000000000 w
b10000 s
b10001 v
b100 r
b100 >
1^
1_
1T
0H
b10100 c
1b
b11000 #
b11000 :
b11000 a
b1100 *
b100000 $"
1)
#250000
0)
