risac.v
module risac (
  input						clk, rst_n,
  output	[31:0] 	oIbusAddr,
  input		[31:0] 	iIbusData,
  input		[31:0]	iIbusIAddr,
  input						iIbusWait,
  output          oIbusRead,
  
  output	[31:0]	oDbusAddr,
  output					oDbusWe,
  output	[31:0]	oDbusData,
  output					oDbusRead,
  output	[3:0]		oDbusByteEn,
  input		[31:0]	iDbusData,
  input						iDbusWait
);

  // ===========================================================
  // the instruction address generation logic
  // pc contains the byte address
  reg [31:0] pc;
  reg [31:0] branchTarget;
  reg branch;
  reg dataHazard;
  reg stallPipe;
  reg pcChanged;
  
  assign oIbusAddr = pc;
  // wait for waitrequest to fall before zeroing
  // read (i.e.) wait till a pending request is completed
  assign oIbusRead = iIbusWait ? 1'b1 : pcChanged;

  always @ (posedge clk or negedge rst_n) begin 
    if (!rst_n) begin 
      pc <= 'b0;
      pcChanged <= 'b1;
    end	else if (!stallPipe && !dataHazard) begin 
      // new data arrives when wait is 0
      // so update pc when wait is 0
      pc <= iIbusWait ? pc : (branch ? branchTarget : pc + 3'd4);

      // assert read regardless of wait
      // but only when pc is updated
      // also dont deassert when wait is high
      // pcChanged <= iIbusWait ? 1'b0 : 1'b1;
      if (!iIbusWait) begin 
        pcChanged <= 1'b1;
      end else begin 
        pcChanged <= 1'b0;
      end
    end else begin
      pcChanged <= 1'b0;
    end
  end

  // ===========================================================
  // decode the instruction 
  // for now support only rtype, itype and stype

  reg [3:0]		aluOpDec;
  reg [4:0]		rs1Dec, rs2Dec, rdDec;
  reg [31:0]	immDec, pcDec, rs1ShiftDec, rs2ShiftDec, rdShiftDec;
  reg 				validDec;
  reg					immSelDec;
  reg 				rdWeDec;
  reg					illegalDec;
  reg					lDec, sDec, luipcDec, luiDec;
  reg         branchDec;

  always @ (posedge clk or negedge rst_n) begin 
    if (!rst_n) begin 
      {aluOpDec, rs1Dec, rs2Dec, immDec, validDec, immSelDec, rdShiftDec} <= 'b0;
      {rdWeDec, illegalDec, pcDec, lDec, sDec, rs1ShiftDec, rs2ShiftDec} <= 'b0; 
      {luipcDec, luiDec, branchDec} <= 'b0;
    end else if (!stallPipe && !dataHazard) begin 
      // the address of the currently being decoded instruction
      pcDec			<= iIbusIAddr;

      // the instruction is valid if there is not wait signal
      validDec	<= ~iIbusWait;

      // decode the instruction regardless of validity

      // lui and auipc are special
      luipcDec <= iIbusData[4:2] == 3'b101;
      luiDec   <= iIbusData[5:2] == 4'b1101;

      // alu op is always [14:12]
      aluOpDec[2:0]	<= iIbusData[14:12];
      aluOpDec[3]		<= iIbusData[30];

      // rs1, rs2 and rd are fixed
      rs1Dec			<= iIbusData[19:15];
      rs2Dec			<= iIbusData[24:20];
      rs1ShiftDec	<= 1 << iIbusData[19:15];
      rs2ShiftDec <= 1 << iIbusData[24:20];
      rdDec				<= iIbusData[11:7];
      rdShiftDec 	<= 1 << iIbusData[11:7];

      // always write to rd except when storing or branching
      // we cater only stores for now 
      rdWeDec		<= (iIbusData[6:2] != 5'b01000);
      
      // select imm when instr[6:4] == 001
      // in rv32i, no other instruction has opcode[6:4] == 001 other than those
      // that use imm
      // lui also uses imm
      immSelDec	<= (iIbusData[6:4] == 3'b001) | (iIbusData[6:2] == 5'b01101);

      // for the imm, use the opcode
      case (iIbusData[6:2]) // the last 2 bits are always 1 anyway
      
      // itype load
      5'b00000: immDec <= { {21{iIbusData[31]}}, iIbusData[30:20] };
      // itype alu
      5'b00100: immDec <= { {21{iIbusData[31]}}, iIbusData[30:20] };
      // jalr
      5'b11001: immDec <= { {21{iIbusData[31]}}, iIbusData[30:20] };
      
      // SType: store
      5'b01000: immDec <= { {21{iIbusData[31]}}, iIbusData[30:25], iIbusData[11:7] };

      // lui
      // auipc
      5'b01101: immDec <= { iIbusData[31:12], 12'b0 };

      endcase

      // load when all zero opcode
      lDec <= iIbusData[6:2] == 5'b00000;
      sDec <= iIbusData[6:2] == 5'b01000;

      // for now ignore the illegal instruction
      // TODO: add illegal indication
    end
  end

  // ===========================================================
  // fetch the operands from the register file
  // the register file has registered outputs

  // also maintain a RAT to track which registers are dirty
  // if dirty registers are needed, stall the previous stages
  // till clean value arrives and invalidate all the instructions
  // that are sent forward 

  reg [31:0]	registers [0:31];
  reg [31:0]	rs1Data, rs2Data, rdShiftEx;
  
  // data hazard handling mech
  reg [31:0]  rat [0:1];
  reg 				stallDataHazard;
  reg         falseAlarm;

  reg 				validEx, rdWeEx;

  integer idx;

  always @ (posedge clk or negedge rst_n) begin: RAT
    if (!rst_n) begin 
      rat[0] <= 'b0;
      rat[1] <= 'b0;
      falseAlarm <= 'b0;
    end else if (!stallPipe) begin
      // update rat
      // set rd'th bit to 1 in rat[0..1]
      // if it is 1 then set it 1 anyway
      // set the rdEx'th bit to 0 in rat[0..1]
      // setting 1 takes priority

      // the zero register is always clean
      rat[0][0] <= 1'b0;
      rat[1][0] <= 1'b0;

      // on the condition that if rat[rd] is already 1 then 
      // 1. add x2, x1, x3
      // 2. add x2, x2, x4
      // when 1 is written back, rat[2] is set to 1 instead of 0
      // because 2 will force it
      // in this case, we must allow only 1 instruction to pass
      // we use a false alarm bit for this

      // raise false alarm when rdDec == rdEx and all the valid conditions
      // also set false alarm to zero if it is one
      if (falseAlarm) begin 
        falseAlarm <= 1'b0;
      end else if (rdWeDec && validDec && rdWeEx) begin 
        falseAlarm <= rdEx == rdDec;
      end

      for (idx = 1; idx < 32; idx = idx + 1) begin
        // if the register to be updated [(rdDecWe == 1) and (rdShiftDec[idx] == 1)]
        // then set the rat to 1 
        if (rdWeDec && rdShiftDec[idx] && validDec) begin 
          rat[0][idx] <= 1'b1;
          rat[1][idx] <= 1'b1;
        end
        // else if the register is *being* updated [(rdExWe == 1) and (rdShiftEx[idx] == 1)]
        // then set the rat to 0
        else if (rdWeEx && rdShiftEx[idx] && validEx) begin 
          rat[0][idx] <= 1'b0;
          rat[1][idx] <= 1'b0;
        end				
      end
    end
  end

  // combinational part 
  reg rs1booked;
  reg rs2booked;
  always @ (*) begin 
    // check if rs1 and rs2 are 'booked'
    rs1booked = |(rs1ShiftDec & rat[0]) && ~luipcDec;
    rs2booked = |(rs2ShiftDec & rat[1]) && ~immSelDec;

    // rs1booked = rat[0][rs1Dec] && ~luipcDec && !(rdWeEx && rdShiftEx[rs1Dec] && validEx);
    // rs2booked = rat[1][rs2Dec] && ~immSelDec && !(rdWeEx && rdShiftEx[rs2Dec] && validEx);
    
    // data hazard occurs when rs1 or rs2 is booked and nothing is being written
    // to the regfile 
    // if there is data being written to the reg file then no need to stall, let it
    // pass
    dataHazard = falseAlarm ? 1'b0 : (rs1booked) | (rs2booked);
  end
  
  // when the data hazard occurs, set valid to zero and stall previous stages

  // propogate the rdWe, valid, aluOp, immSel, pc and imm signals
  reg					validOf, rdWeOf, immSelOf;	
  reg [31:0]	immOf, pcOf;
  reg [3:0]		aluOpOf;
  reg [4:0]		rdOf;
  reg 				lOf, sOf, luipcOf;
  reg         branchOf;

  always @ (posedge clk or negedge rst_n) begin 
    if (!rst_n) begin 
      {rs1Data, rs2Data, validOf, rdWeOf, immOf} <= 'b0;
      {pcOf, immSelOf, aluOpOf, rdOf, lOf, sOf, luipcOf, branchOf} <= 'b0;
      // !do not reset the registers!!

    end else if (!stallPipe) begin 
      // propogation
      {rdWeOf, immOf} <= {rdWeDec, immDec};
      {immSelOf, rdOf} <= {immSelDec, rdDec};
      {lOf, sOf, luipcOf} <= {lDec, sDec, luipcDec};
      branchOf <= branchDec;

      if (falseAlarm) begin 
        validOf <= validDec;
      end else begin 
        validOf <= validDec & ~dataHazard;
      end 

      rs1Data <= rs1Dec == 5'b0 ? 32'b0 : registers [rs1Dec];
      rs2Data	<= rs2Dec == 5'b0 ? 32'b0 : registers [rs2Dec];
      aluOpOf <= luipcDec ? 4'b0 : aluOpDec;
      pcOf    <= luiDec ? 32'b0 : pcDec;
    end
  end

  // ============================================================
  // select the operands to feed the alu and lsu
  // add the imm in rs1 to get the address
  // the data to store is in rs2


  reg [31:0] 	aluIn1, aluIn2;

  // propogate the valid, aluOp, rdWe, pc
  reg [31:0] 	pcOs;
  reg [3:0]		aluOpOs;
  reg 				validOs, rdWeOs;
  reg [4:0]		rdOs;
  reg 				lOs, sOs;
  reg [31:0]	lsuAddrOs, lsuDataOs;

  always @ (posedge clk or negedge rst_n) begin 
    if (!rst_n) begin 
      {pcOs, aluOpOs, validOs, rdWeOs, rdOs} <= 'b0;
      {aluIn1, aluIn2, lOs, sOs, lsuAddrOs, lsuDataOs} <= 'b0;
      {branch, branchTarget} <= 'b0;
    end else if (!stallPipe) begin 
      {pcOs, validOs, rdWeOs, rdOs} <= {pcOf, validOf, rdWeOf, rdOf};
      {lOs, sOs} <= {lOf, sOf};

      branch <= branchOf;

      lsuAddrOs <= rs1Data + immOf;
      lsuDataOs <= rs2Data;

      // when lui comes, the imm is the value 
      // so zero aluIn1 and set operation to add
      aluIn1	<= luipcOf ? pcOf : rs1Data;

      // aluIn2 is between imm and rs2Data
      aluIn2	<= immSelOf ? immOf : rs2Data;

      // if IType and the operation is add then clear op[3],
      // coz there is no subi 
      if (immSelOf && (aluOpOf[2:0] == 3'b000))
        aluOpOs[3] <= 1'b0;
      else 
        aluOpOs[3] <= aluOpOf[3];

      aluOpOs[2:0] <= aluOpOf[2:0]; 
    end
  end

  // ============================================================
  // the execute stage
  // can have multiple units in paralell
  // for now we only have the alu and lsu 
  reg [31:0] exRes;

  // propogate the valid, pc, rdWe
  reg [31:0]	pcEx;
  reg [4:0]		rdEx;

  always @ (posedge clk or negedge rst_n) begin 
    if (!rst_n) begin 
      {pcEx, validEx, rdWeEx, rdEx, rdShiftEx} <= 'b0;
    end else if (!stallPipe) begin
      {pcEx, validEx, rdWeEx, rdEx} <= {pcOs, validOs, rdWeOs, rdOs};
      rdShiftEx <= 1 << rdOs;			
    end
  end

  // ============================================================
  // the alu has a fixed latency of 1
  // the alu causes no stalls
  reg [31:0]	aluRes;

  always @ (posedge clk or negedge rst_n) begin 
    if (!rst_n) begin 
      aluRes <= 'b0;
    end else begin 
      case (aluOpOs[2:0])
      3'b000: aluRes <= aluOpOs[3] ? aluIn1 - aluIn2 : aluIn1 + aluIn2;	// add/sub
      3'b001: aluRes <= aluIn1 << aluIn2[4:0];	// sll
      3'b010: aluRes <= $signed(aluIn1) < $signed(aluIn2) ? 32'b1 : 32'b0; 
      3'b011: aluRes <= aluIn1 < aluIn2 ? 32'b1 : 32'b0;
      3'b100: aluRes <= aluIn1 ^ aluIn2;
      3'b101: aluRes <= aluOpOs[3] ? $signed($signed(aluIn1) >>> aluIn2[4:0]) : aluIn1 >> aluIn2[4:0];
      3'b110: aluRes <= aluIn1 | aluIn2;
      3'b111: aluRes <= aluIn1 & aluIn2;
      endcase
    end 
  end

  // ============================================================
  // the lsu has min latency of 1 
  // max latency of infinity
  // lsu can stall the pipeline 
  // data to store in rs2

  reg [31:0]	lsuRes;
  reg 				lsuStall;
  reg [3:0]		lsuByteEn;
  reg 				lEx;

  assign oDbusAddr 		= lsuAddrOs;
  assign oDbusRead 		= lOs & validOs;
  assign oDbusWe	 		= sOs & validOs;
  assign oDbusData 		= lsuDataOs;
  assign oDbusByteEn 	= lsuByteEn;

  // wait only asserted when reading, writing does not assert wait
  // from m4k, reads have min latency of 1

  always @ (*) begin 
    lsuStall = iDbusWait & (lOs | sOs) & validOs;
  
    case (aluOpOs[1:0]) 
    2'b00:	lsuByteEn = 4'b1;			// sb/lb
    2'b01:	lsuByteEn = 4'b11;		// sh/lh
    2'b10:	lsuByteEn	= 4'b1111;	// sw/lw
    default:lsuByteEn = 4'b0;	
    endcase
  end

  always @ (posedge clk or negedge rst_n) begin 
    if (!rst_n) begin 
      lsuRes 	<= 'b0;
      lEx 		<= 'b0;
    end	else if (!stallPipe) begin 
      lEx 		<= lOs;
      if (aluOpOs[1]) begin  // lw
        lsuRes <= iDbusData;
      end else begin 
        case ({aluOpOs[2], aluOpOs[0]}) 
        2'b00: lsuRes <= { {24{iDbusData[07]}}, iDbusData[07:0] };	// lb
        2'b01: lsuRes <= { {16{iDbusData[15]}}, iDbusData[15:0] };	// lh
        2'b10: lsuRes <= { 24'b0, iDbusData[07:0] };	// lbu
        2'b11: lsuRes <= { 16'b0, iDbusData[15:0] };	// lhu 
        endcase
      end
    end
  end

  // ============================================================
  // the stall handling mech,
  // simply or the stalls from all the sources
  // for now, only lsu can stall
  // IF doesn't stall, it keeps sending invalid instructions
  // which don't affect anything

  always @ (*) begin 
    stallPipe = lsuStall;
  end	

  // ============================================================
  // the write back stage

  // mux the result from various stages
  // for now, if load instruction, then select lsuRes
  always @ (*) begin 
    exRes	= lEx ? lsuRes : aluRes;
  end

  always @ (posedge clk) begin 
    // do not reset the register file
    // write back if valid only
    if (validEx && rdWeEx) begin 
      registers[rdEx] <= exRes;
    end
  end
endmodule

testbench/risac_tb_single_mem.v
`timescale 1ns / 1ps

module testbench();

  reg						clk = 1, rst_n = 0;
  wire	[31:0] 	oIbusAddr;
  reg		[31:0] 	iIbusData;
  reg		[31:0]	iIbusIAddr;
  reg						iIbusWait;
  
  wire	[31:0]	oDbusAddr;
  wire					oDbusWe;
  wire	[31:0]	oDbusData;
  wire					oDbusRead;
  wire	[3:0]		oDbusByteEn;
  reg		[31:0]	iDbusData;
  reg						iDbusWait;

  risac u_risac (
    .clk          (clk),
    .rst_n        (rst_n),

    // The IBUS

    .oIbusAddr    (oIbusAddr),
    .iIbusData    (iIbusData),
    .iIbusIAddr   (iIbusIAddr),
    .iIbusWait    (iIbusWait),
    
    // The DBUS

    .oDbusAddr    (oDbusAddr),
    .oDbusWe      (oDbusWe),
    .oDbusData    (oDbusData),
    .oDbusRead    (oDbusRead),
    .oDbusByteEn  (oDbusByteEn),
    .iDbusData    (iDbusData),
    .iDbusWait    (iDbusWait)
  );


  reg [7:0] mem [0:4095]; // 4K ram
  reg [31:0] cnt = 0;

  // create a clock
  always @ (posedge clk) begin 
    cnt = cnt + 1;
  end

  always begin 
    #10 
    clk = !clk;
  end

  // initialize the memories
  integer i;
  initial begin 
    // prepare a vcd dump
    $dumpfile("risac2.vcd");
    $dumpvars(0, testbench);
    $readmemh("program.vh", mem);

    $display ("\n======================");
    $display ("RISCV Virtual Terminal");
    $display ("======================\n"); 
    
    #5
    rst_n = 1'b1;



    #5000 
    // dump memory to output 
    $display ("======================\n"); 
    
    $finish;
  end

  // create a memory system
  // simple zero latency memory

  // ==========================
  // the instruction bus
  // ==========================

  always @ (oIbusAddr) begin 
    iIbusWait <= 1'b0;
    iIbusData <= {mem [oIbusAddr+3], mem [oIbusAddr+2], mem [oIbusAddr+1], mem [oIbusAddr]};
    iIbusIAddr<= oIbusAddr;
  end


  reg [7:0]  dmem_addr;
  reg [31:0] and_mask;

  always @ (cnt) begin 
    // the virtual console 
    if (oDbusWe && oDbusAddr == 32'h10000 && oDbusByteEn[0]) begin 
      $write("%c", oDbusData[7:0]);		
    end
  end 

  reg [31:0] oldWord;

  always @ (*) begin 
    iDbusData = 'b0;
    iDbusWait = 'b0;
    
    if (oDbusWe) begin 
      mem[oDbusAddr]     = oDbusByteEn[0] ? oDbusData[07:00] : mem[oDbusAddr];
      mem[oDbusAddr + 1] = oDbusByteEn[1] ? oDbusData[15:08] : mem[oDbusAddr + 1];
      mem[oDbusAddr + 2] = oDbusByteEn[2] ? oDbusData[23:16] : mem[oDbusAddr + 2];
      mem[oDbusAddr + 3] = oDbusByteEn[3] ? oDbusData[31:24] : mem[oDbusAddr + 3];
    end
    
    if (oDbusRead) begin 
      iDbusData = {mem[oDbusAddr + 3], mem[oDbusAddr + 2], mem[oDbusAddr + 1], mem[oDbusAddr]};
    end
  end

endmodule

testbench/risac.vcd
$date
	Sun Nov 17 11:35:09 2019
$end
$version
	Icarus Verilog
$end
$timescale
	1ps
$end
$scope module testbench $end
$var wire 32 ! oIbusAddr [31:0] $end
$var wire 1 " oDbusWe $end
$var wire 1 # oDbusRead $end
$var wire 32 $ oDbusData [31:0] $end
$var wire 4 % oDbusByteEn [3:0] $end
$var wire 32 & oDbusAddr [31:0] $end
$var reg 1 ' clk $end
$var reg 32 ( cnt [31:0] $end
$var reg 8 ) dmem_addr [7:0] $end
$var reg 32 * iDbusData [31:0] $end
$var reg 1 + iDbusWait $end
$var reg 32 , iIbusData [31:0] $end
$var reg 32 - iIbusIAddr [31:0] $end
$var reg 1 . iIbusWait $end
$var reg 32 / oldWord [31:0] $end
$var reg 1 0 rst_n $end
$var integer 32 1 i [31:0] $end
$scope module u_risac $end
$var wire 1 ' clk $end
$var wire 32 2 iDbusData [31:0] $end
$var wire 1 + iDbusWait $end
$var wire 32 3 iIbusData [31:0] $end
$var wire 32 4 iIbusIAddr [31:0] $end
$var wire 1 . iIbusWait $end
$var wire 32 5 oDbusAddr [31:0] $end
$var wire 4 6 oDbusByteEn [3:0] $end
$var wire 32 7 oDbusData [31:0] $end
$var wire 1 # oDbusRead $end
$var wire 1 " oDbusWe $end
$var wire 32 8 oIbusAddr [31:0] $end
$var wire 1 0 rst_n $end
$var wire 1 9 oIbusRead $end
$var reg 32 : aluIn1 [31:0] $end
$var reg 32 ; aluIn2 [31:0] $end
$var reg 4 < aluOpDec [3:0] $end
$var reg 4 = aluOpOf [3:0] $end
$var reg 4 > aluOpOs [3:0] $end
$var reg 32 ? aluRes [31:0] $end
$var reg 1 @ branch $end
$var reg 1 A branchDec $end
$var reg 1 B branchOf $end
$var reg 32 C branchTarget [31:0] $end
$var reg 1 D dataHazard $end
$var reg 32 E exRes [31:0] $end
$var reg 1 F falseAlarm $end
$var reg 1 G illegalDec $end
$var reg 32 H immDec [31:0] $end
$var reg 32 I immOf [31:0] $end
$var reg 1 J immSelDec $end
$var reg 1 K immSelOf $end
$var reg 1 L lDec $end
$var reg 1 M lEx $end
$var reg 1 N lOf $end
$var reg 1 O lOs $end
$var reg 32 P lsuAddrOs [31:0] $end
$var reg 4 Q lsuByteEn [3:0] $end
$var reg 32 R lsuDataOs [31:0] $end
$var reg 32 S lsuRes [31:0] $end
$var reg 1 T lsuStall $end
$var reg 1 U luiDec $end
$var reg 1 V luipcDec $end
$var reg 1 W luipcOf $end
$var reg 32 X pc [31:0] $end
$var reg 1 Y pcChanged $end
$var reg 32 Z pcDec [31:0] $end
$var reg 32 [ pcEx [31:0] $end
$var reg 32 \ pcOf [31:0] $end
$var reg 32 ] pcOs [31:0] $end
$var reg 5 ^ rdDec [4:0] $end
$var reg 5 _ rdEx [4:0] $end
$var reg 5 ` rdOf [4:0] $end
$var reg 5 a rdOs [4:0] $end
$var reg 32 b rdShiftDec [31:0] $end
$var reg 32 c rdShiftEx [31:0] $end
$var reg 1 d rdWeDec $end
$var reg 1 e rdWeEx $end
$var reg 1 f rdWeOf $end
$var reg 1 g rdWeOs $end
$var reg 32 h rs1Data [31:0] $end
$var reg 5 i rs1Dec [4:0] $end
$var reg 32 j rs1ShiftDec [31:0] $end
$var reg 1 k rs1booked $end
$var reg 32 l rs2Data [31:0] $end
$var reg 5 m rs2Dec [4:0] $end
$var reg 32 n rs2ShiftDec [31:0] $end
$var reg 1 o rs2booked $end
$var reg 1 p sDec $end
$var reg 1 q sOf $end
$var reg 1 r sOs $end
$var reg 1 s stallPipe $end
$var reg 1 t validDec $end
$var reg 1 u validEx $end
$var reg 1 v validOf $end
$var reg 1 w validOs $end
$var integer 32 x idx [31:0] $end
$scope begin RAT $end
$upscope $end
$upscope $end
$upscope $end
$enddefinitions $end
#0
$dumpvars
bx x
0w
0v
0u
0t
0s
0r
0q
0p
0o
b0 n
b0 m
b0 l
0k
b0 j
b0 i
b0 h
0g
0f
0e
0d
b0 c
b0 b
b0 a
b0 `
b0 _
bx ^
b0 ]
b0 \
b0 [
b0 Z
1Y
b0 X
0W
0V
0U
0T
b0 S
b0 R
b1 Q
b0 P
0O
0N
0M
0L
0K
0J
b0 I
b0 H
0G
0F
b0 E
0D
b0 C
0B
0A
0@
b0 ?
b0 >
b0 =
b0 <
b0 ;
b0 :
19
b0 8
b0 7
b1 6
b0 5
b0 4
b100100000000000010100010011 3
b0 2
bx 1
00
bx /
0.
b0 -
b100100000000000010100010011 ,
0+
b0 *
b0 )
b0 (
1'
b0 &
b1 %
b0 $
0#
0"
b0 !
$end
#5000
10
#10000
0'
#20000
b100 -
b100 4
b101000000010000000100011 ,
b101000000010000000100011 3
b1 c
bx `
b1001000 H
1J
1d
b10000000000 b
b1010 ^
b100000000 n
b1 j
b1000 m
1t
b100 !
b100 8
b100 X
b1 (
b100000 x
1'
#30000
0'
#40000
b1000 -
b1000 4
b110010100000000010100010011 ,
b110010100000000010100010011 3
1D
1o
b1000 !
b1000 8
b1000 X
1p
b0 H
0J
0d
b1 b
b0 ^
b10000000000 n
b1010 m
b10 <
b100 Z
bx l
1v
1K
b1010 `
1f
b1001000 I
bx a
b10 (
b100000 x
1'
#50000
0'
#60000
b10010 )
09
bx c
bx _
b1001000 ;
bx $
bx 7
bx R
b1001000 &
b1001000 5
b1001000 P
1w
1g
b1010 a
b100 \
b10 =
0v
1q
0K
b0 `
0f
b0 I
0Y
b11 (
b100000 x
1'
#70000
0'
#80000
b0 )
b1111 %
b1111 6
b1111 Q
b1001000 E
b10 >
bx ;
b0 &
b0 5
b0 P
1r
b100 ]
0w
0g
b0 a
b10000000000 c
1u
1e
b1010 _
b1001000 ?
b100 (
b100000 x
1'
#90000
0'
#100000
0D
0o
b0x E
b0x ?
b1 c
b100 [
0u
0e
b0 _
b101 (
b100000 x
1'
#110000
0'
#120000
b1100 -
b1100 4
b101000000010000000100011 ,
b101000000010000000100011 3
19
1Y
b1100 !
b1100 8
b1100 X
0p
b1100101 H
1J
1d
b10000000000 b
b1010 ^
b100000 n
b101 m
b0 <
b1000 Z
b1001000 l
1v
b110 (
b100000 x
1'
#130000
0'
#140000
b10000 -
b10000 4
b110110000000000010100010011 ,
b110110000000000010100010011 3
b0 /
1"
1D
1o
b1001000 ;
b1001000 $
b1001000 7
b1001000 R
1w
b1000 \
b0 =
bx l
0q
1K
b1010 `
1f
b1100101 I
1p
b0 H
0J
0d
b1 b
b0 ^
b10000000000 n
b1010 m
b10 <
b1100 Z
b10000 !
b10000 8
b10000 X
b111 (
b100000 x
1'
#150000
0'
#160000
09
b11001 )
b1 %
b1 6
b1 Q
0"
b1 E
0Y
b1100 \
b10 =
b1001000 l
0v
1q
0K
b0 `
0f
b0 I
b0 >
b1100101 ;
bx $
bx 7
bx R
b1100101 &
b1100101 5
b1100101 P
0r
b1000 ]
1g
b1010 a
1u
b1 ?
b1000 (
b100000 x
1'
#170000
0'
#180000
b1100101 E
b0 )
b1111 %
b1111 6
b1111 Q
b1100101 ?
b10000000000 c
b1000 [
1e
b1010 _
b10 >
b1001000 ;
b1001000 $
b1001000 7
b1001000 R
b0 &
b0 5
b0 P
1r
b1100 ]
0w
0g
b0 a
b1001 (
b100000 x
1'
#190000
0'
#200000
0D
0o
b1 E
b1 c
b1100 [
0u
0e
b0 _
b1 ?
b1010 (
b100000 x
1'
#210000
0'
#220000
b10100 -
b10100 4
b101000000010000000100011 ,
b101000000010000000100011 3
19
b1100101 l
1v
0p
b1101100 H
1J
1d
b10000000000 b
b1010 ^
b1000000000000 n
b1100 m
b0 <
b10000 Z
1Y
b10100 !
b10100 8
b10100 X
b1011 (
b100000 x
1'
#230000
0'
#240000
b11000 -
b11000 4
1D
1o
b1001000 /
1"
b11000 !
b11000 8
b11000 X
1p
b0 H
0J
0d
b1 b
b0 ^
b10000000000 n
b1010 m
b10 <
b10100 Z
b10000 \
b0 =
bx l
0q
1K
b1010 `
1f
b1101100 I
b1100101 ;
b1100101 $
b1100101 7
b1100101 R
1w
b1100 (
b100000 x
1'
#250000
0'
#260000
b11011 )
b1 %
b1 6
b1 Q
0"
09
1u
b0 >
b1101100 ;
bx $
bx 7
bx R
b1101100 &
b1101100 5
b1101100 P
0r
b10000 ]
1g
b1010 a
b10100 \
b10 =
b1100101 l
0v
1q
0K
b0 `
0f
b0 I
0Y
b1101 (
b100000 x
1'
#270000
0'
#280000
b0 )
b1111 %
b1111 6
b1111 Q
b1101100 E
b10 >
b1100101 ;
b1100101 $
b1100101 7
b1100101 R
b0 &
b0 5
b0 P
1r
b10100 ]
0w
0g
b0 a
b10000000000 c
b10000 [
1e
b1010 _
b1101100 ?
b1110 (
b100000 x
1'
#290000
0'
#300000
0D
0o
b1 E
b1 ?
b1 c
b10100 [
0u
0e
b0 _
b1111 (
b100000 x
1'
#310000
0'
#320000
b11100 -
b11100 4
b110111100000000010110010011 ,
b110111100000000010110010011 3
19
1Y
b11100 !
b11100 8
b11100 X
b11000 Z
b1101100 l
1v
b10000 (
b100000 x
1'
#330000
0'
#340000
b100000 -
b100000 4
b101100000010000000100011 ,
b101100000010000000100011 3
b1100101 /
1"
b1101100 ;
b1101100 $
b1101100 7
b1101100 R
1w
b11000 \
0p
b1101111 H
1J
1d
b100000000000 b
b1011 ^
b1000000000000000 n
b1111 m
b0 <
b11100 Z
b100000 !
b100000 8
b100000 X
b10001 (
b100000 x
1'
#350000
0'
#360000
b100100 -
b100100 4
b10110000000000011000010011 ,
b10110000000000011000010011 3
1D
1o
b100100 !
b100100 8
b100100 X
1p
b0 H
0J
0d
b1 b
b0 ^
b100000000000 n
b1011 m
b10 <
b100000 Z
b11100 \
b0 =
bx l
0q
1K
b1011 `
1f
b1101111 I
b11000 ]
1u
b10010 (
b100000 x
1'
#370000
0'
#380000
b11011 )
b1 %
b1 6
b1 Q
0"
09
b11000 [
b0 >
b1101111 ;
bx $
bx 7
bx R
b1101111 &
b1101111 5
b1101111 P
0r
b11100 ]
1g
b1011 a
b100000 \
b10 =
0v
1q
0K
b0 `
0f
b0 I
0Y
b10011 (
b100000 x
1'
#390000
0'
#400000
b0 )
b1111 %
b1111 6
b1111 Q
b1101111 E
b10 >
bx ;
b0 &
b0 5
b0 P
1r
b100000 ]
0w
0g
b0 a
b100000000000 c
b11100 [
1e
b1011 _
b1101111 ?
b10100 (
b100000 x
1'
#410000
0'
#420000
0D
0o
b0x E
b0x ?
b1 c
b100000 [
0u
0e
b0 _
b10101 (
b100000 x
1'
#430000
0'
#440000
b101000 -
b101000 4
b110000000010000000100011 ,
b110000000010000000100011 3
19
1Y
b101000 !
b101000 8
b101000 X
0p
b101100 H
1J
1d
b1000000000000 b
b1100 ^
b1000000000000 n
b1100 m
b0 <
b100100 Z
b1101111 l
1v
b10110 (
b100000 x
1'
#450000
0'
#460000
b101100 -
b101100 4
b10000000000000011000010011 ,
b10000000000000011000010011 3
b1101100 /
1"
1D
1o
b1101111 ;
b1101111 $
b1101111 7
b1101111 R
1w
b100100 \
b0 =
bx l
0q
1K
b1100 `
1f
b101100 I
1p
b0 H
0J
0d
b1 b
b0 ^
b10 <
b101000 Z
b101100 !
b101100 8
b101100 X
b10111 (
b100000 x
1'
#470000
0'
#480000
09
b1011 )
b1 %
b1 6
b1 Q
0"
b1 E
0Y
b101000 \
b10 =
0v
1q
0K
b0 `
0f
b0 I
b0 >
b101100 ;
bx $
bx 7
bx R
b101100 &
b101100 5
b101100 P
0r
b100100 ]
1g
b1100 a
1u
b1 ?
b11000 (
b100000 x
1'
#490000
0'
#500000
b101100 E
b0 )
b1111 %
b1111 6
b1111 Q
b101100 ?
b1000000000000 c
b100100 [
1e
b1100 _
b10 >
bx ;
b0 &
b0 5
b0 P
1r
b101000 ]
0w
0g
b0 a
b11001 (
b100000 x
1'
#510000
0'
#520000
0D
0o
b0x E
b1 c
b101000 [
0u
0e
b0 _
b0x ?
b11010 (
b100000 x
1'
#530000
0'
#540000
b110000 -
b110000 4
b110000000010000000100011 ,
b110000000010000000100011 3
19
b101100 l
1v
0p
b100000 H
1J
1d
b1000000000000 b
b1100 ^
b1 n
b0 m
b0 <
b101100 Z
1Y
b110000 !
b110000 8
b110000 X
b11011 (
b100000 x
1'
#550000
0'
#560000
b110100 -
b110100 4
b101011100000000011000010011 ,
b101011100000000011000010011 3
1D
1o
b1101111 /
1"
b110100 !
b110100 8
b110100 X
1p
b0 H
0J
0d
b1 b
b0 ^
b1000000000000 n
b1100 m
b10 <
b110000 Z
b101100 \
b0 =
b0 l
0q
1K
b1100 `
1f
b100000 I
b101100 ;
b101100 $
b101100 7
b101100 R
1w
b11100 (
b100000 x
1'
#570000
0'
#580000
b1 E
b1000 )
b1 %
b1 6
b1 Q
0"
09
b1 ?
1u
b0 >
b100000 ;
b0 $
b0 7
b0 R
b100000 &
b100000 5
b100000 P
0r
b101100 ]
1g
b1100 a
b110000 \
b10 =
b101100 l
0v
1q
0K
b0 `
0f
b0 I
0Y
b11101 (
b100000 x
1'
#590000
0'
#600000
b0 )
b1111 %
b1111 6
b1111 Q
b100000 E
b10 >
b101100 ;
b101100 $
b101100 7
b101100 R
b0 &
b0 5
b0 P
1r
b110000 ]
0w
0g
b0 a
b1000000000000 c
b101100 [
1e
b1100 _
b100000 ?
b11110 (
b100000 x
1'
#610000
0'
#620000
0D
0o
b1 E
b1 ?
b1 c
b110000 [
0u
0e
b0 _
b11111 (
b100000 x
1'
#630000
0'
#640000
b111000 -
b111000 4
b110000000010000000100011 ,
b110000000010000000100011 3
19
1Y
b111000 !
b111000 8
b111000 X
0p
b1010111 H
1J
1d
b1000000000000 b
b1100 ^
b100000000000000000000000 n
b10111 m
b0 <
b110100 Z
b100000 l
1v
b100000 (
b100000 x
1'
#650000
0'
