risac.v
module risac (
  input						clk, rst_n,
  output	[31:0] 	oIbusAddr,
  input		[31:0] 	iIbusData,
  input		[31:0]	iIbusIAddr,
  input						iIbusWait,
  output          oIbusRead,
  
  output	[31:0]	oDbusAddr,
  output					oDbusWe,
  output	[31:0]	oDbusData,
  output					oDbusRead,
  output	[3:0]		oDbusByteEn,
  input		[31:0]	iDbusData,
  input						iDbusWait
);

  // ===========================================================
  // the instruction address generation logic
  // pc contains the byte address
  reg [31:0] pc;
  reg [31:0] branchTarget;
  reg branch;
  reg dataHazard;
  reg stallPipe;
  reg pcChanged;
  
  assign oIbusAddr = pc;
  // wait for waitrequest to fall before zeroing
  // read (i.e.) wait till a pending request is completed
  assign oIbusRead = iIbusWait ? 1'b1 : pcChanged;

  always @ (posedge clk or negedge rst_n) begin: IF
    if (!rst_n) begin 
      pc <= 'b0;
      pcChanged <= 'b1;
    end	else if (!stallPipe && !dataHazard) begin 
      // new data arrives when wait is 0
      // so update pc when wait is 0
      pc <= iIbusWait ? pc : (branch ? branchTarget : pc + 3'd4);

      // assert read regardless of wait
      // but only when pc is updated
      // also dont deassert when wait is high
      // pcChanged <= iIbusWait ? 1'b0 : 1'b1;
      if (!iIbusWait) begin 
        pcChanged <= 1'b1;
      end else begin 
        pcChanged <= 1'b0;
      end
    end else begin
      pcChanged <= 1'b0;
    end
  end

  // ===========================================================
  // decode the instruction 
  // for now support only rtype, itype and stype

  reg [3:0]		aluOpDec;
  reg [4:0]		rs1Dec, rs2Dec, rdDec;
  reg [31:0]	immDec, pcDec, rs1ShiftDec, rs2ShiftDec, rdShiftDec;
  reg 				validDec;
  reg					immSelDec;
  reg 				rdWeDec;
  reg					illegalDec;
  reg					lDec, sDec, luipcDec, luiDec;
  reg         branchDec;
  reg         branchType;

  always @ (posedge clk or negedge rst_n) begin: DEC
    if (!rst_n) begin 
      {aluOpDec, rs1Dec, rs2Dec, immDec, validDec, immSelDec, rdShiftDec} <= 'b0;
      {rdWeDec, illegalDec, pcDec, lDec, sDec, rs1ShiftDec, rs2ShiftDec} <= 'b0; 
      {luipcDec, luiDec, branchDec, branchType} <= 'b0;
    end else if (!stallPipe && !dataHazard) begin 
      // the address of the currently being decoded instruction
      pcDec			<= iIbusIAddr;

      // the instruction is valid if there is not wait signal
      validDec	<= ~iIbusWait;

      // decode the instruction regardless of validity

      // branch instructions
      // only branch opcodes begin with 110
      branchDec   <= iIbusData[6:4] == 3'b110;
      // for unconditional branches, the next 2 bits are zero
      // branchType: zero for unconditional, 1 for conditional
      // for all branches, pc <= pc + offset
      // except jalr, pc <= rs1 + offset 
      branchType  <= iIbusData[3:2] == 2'b00;

      // lui and auipc are special
      luipcDec <= iIbusData[4:2] == 3'b101;
      luiDec   <= iIbusData[5:2] == 4'b1101;

      // alu op is always [14:12]
      aluOpDec[2:0]	<= iIbusData[14:12];
      aluOpDec[3]		<= iIbusData[30];

      // rs1, rs2 and rd are fixed
      rs1Dec			<= iIbusData[19:15];
      rs2Dec			<= iIbusData[24:20];
      rs1ShiftDec	<= 1 << iIbusData[19:15];
      rs2ShiftDec <= 1 << iIbusData[24:20];
      rdDec				<= iIbusData[11:7];
      rdShiftDec 	<= 1 << iIbusData[11:7];

      // always write to rd except when storing or conditional branching
      // all instructions except stores and conditional branches have 4:2 
      // not equal to zero
      rdWeDec		<= (iIbusData[4:2] != 3'b000);
      
      // select imm when instr[6:4] == 001
      // in rv32i, no other instruction has opcode[6:4] == 001 other than those
      // that use imm
      // lui also uses imm
      // jalr and jal also use imm
      immSelDec	<=  (iIbusData[6:4] == 3'b001) | 
                    (iIbusData[6:2] == 5'b01101) | 
                    (iIbusData[6:2] == 5'b11011) |
                    (iIbusData[6:2] == 5'b11001);

      // for the imm, use the opcode
      case (iIbusData[6:2]) // the last 2 bits are always 1 anyway
      
      // itype load
      5'b00000: immDec <= { {21{iIbusData[31]}}, iIbusData[30:20] };
      // itype alu
      5'b00100: immDec <= { {21{iIbusData[31]}}, iIbusData[30:20] };
      // jalr
      5'b11001: immDec <= { {21{iIbusData[31]}}, iIbusData[30:20] };
      
      // SType: store
      5'b01000: immDec <= { {21{iIbusData[31]}}, iIbusData[30:25], iIbusData[11:7] };

      // lui
      // auipc
      5'b01101: immDec <= { iIbusData[31:12], 12'b0 };

      // jal
      5'b11011: immDec <= { {12{iIbusData[31]}}, iIbusData[19:12], iIbusData[20], iIbusData[30:25], iIbusData[24:21], 1'b0 };

      // btype, all conditional branches
      5'b11000: immDec <= { {20{iIbusData[31]}}, iIbusData[7], iIbusData[30:25], iIbusData[11:8], 1'b0 };

      endcase

      // load when all zero opcode
      lDec <= iIbusData[6:2] == 5'b00000;
      sDec <= iIbusData[6:2] == 5'b01000;

      // for now ignore the illegal instruction
      // TODO: add illegal indication
    end
  end

  // ===========================================================
  // fetch the operands from the register file
  // the register file has registered outputs

  // also maintain a RAT to track which registers are dirty
  // if dirty registers are needed, stall the previous stages
  // till clean value arrives and invalidate all the instructions
  // that are sent forward 

  reg [31:0]	registers [0:31];
  reg [31:0]	rs1Data, rs2Data, rdShiftEx;
  
  // data hazard handling mech
  reg [31:0]  rat [0:1];
  reg 				stallDataHazard;
  reg         falseAlarm;

  reg 				validEx, rdWeEx;

  integer idx;

  always @ (posedge clk or negedge rst_n) begin: RAT
    if (!rst_n) begin 
      rat[0] <= 'b0;
      rat[1] <= 'b0;
      falseAlarm <= 'b0;
    end else if (!stallPipe) begin
      // update rat
      // set rd'th bit to 1 in rat[0..1]
      // if it is 1 then set it 1 anyway
      // set the rdEx'th bit to 0 in rat[0..1]
      // setting 1 takes priority

      // the zero register is always clean
      rat[0][0] <= 1'b0;
      rat[1][0] <= 1'b0;

      // on the condition that if rat[rd] is already 1 then 
      // 1. add x2, x1, x3
      // 2. add x2, x2, x4
      // when 1 is written back, rat[2] is set to 1 instead of 0
      // because 2 will force it
      // in this case, we must allow only 1 instruction to pass
      // we use a false alarm bit for this

      // raise false alarm when rdDec == rdEx and all the valid conditions
      // also set false alarm to zero if it is one
      if (falseAlarm) begin 
        falseAlarm <= 1'b0;
      end else if (rdWeDec && validDec && rdWeEx) begin 
        falseAlarm <= rdEx == rdDec;
      end

      for (idx = 1; idx < 32; idx = idx + 1) begin
        // if the register to be updated [(rdDecWe == 1) and (rdShiftDec[idx] == 1)]
        // then set the rat to 1 
        if (rdWeDec && rdShiftDec[idx] && validDec) begin 
          rat[0][idx] <= 1'b1;
          rat[1][idx] <= 1'b1;
        end
        // else if the register is *being* updated [(rdExWe == 1) and (rdShiftEx[idx] == 1)]
        // then set the rat to 0
        else if (rdWeEx && rdShiftEx[idx] && validEx) begin 
          rat[0][idx] <= 1'b0;
          rat[1][idx] <= 1'b0;
        end				
      end
    end
  end

  // combinational part 
  reg rs1booked;
  reg rs2booked;
  always @ (*) begin: HAZARD_DETECTION
    // check if rs1 and rs2 are 'booked'
    rs1booked = |(rs1ShiftDec & rat[0]) && ~luipcDec;
    rs2booked = |(rs2ShiftDec & rat[1]) && ~immSelDec;

    // rs1booked = rat[0][rs1Dec] && ~luipcDec && !(rdWeEx && rdShiftEx[rs1Dec] && validEx);
    // rs2booked = rat[1][rs2Dec] && ~immSelDec && !(rdWeEx && rdShiftEx[rs2Dec] && validEx);
    
    // data hazard occurs when rs1 or rs2 is booked and nothing is being written
    // to the regfile 
    // if there is data being written to the reg file then no need to stall, let it
    // pass
    dataHazard = falseAlarm ? 1'b0 : (rs1booked) | (rs2booked);
  end
  
  // when the data hazard occurs, set valid to zero and stall previous stages

  // propogate the rdWe, valid, aluOp, immSel, pc and imm signals
  reg					validOf, rdWeOf, immSelOf;	
  reg [31:0]	immOf, pcOf;
  reg [3:0]		aluOpOf;
  reg [4:0]		rdOf;
  reg 				lOf, sOf, luipcOf;
  reg         branchOf;

  always @ (posedge clk or negedge rst_n) begin: OF
    if (!rst_n) begin 
      {rs1Data, rs2Data, validOf, rdWeOf, immOf} <= 'b0;
      {pcOf, immSelOf, aluOpOf, rdOf, lOf, sOf, luipcOf, branchOf} <= 'b0;
      // !do not reset the registers!!

    end else if (!stallPipe) begin 
      // propogation
      {rdWeOf} <= {rdWeDec};
      {immSelOf, rdOf} <= {immSelDec, rdDec};
      {lOf, sOf, luipcOf} <= {lDec, sDec, luipcDec};
      branchOf <= branchDec & ~branchType;

      if (falseAlarm) begin 
        validOf <= validDec;
      end else begin 
        validOf <= validDec & ~dataHazard;
      end 

      rs1Data <= rs1Dec == 5'b0 ? 32'b0 : registers [rs1Dec];
      rs2Data	<= rs2Dec == 5'b0 ? 32'b0 : registers [rs2Dec];
      aluOpOf <= luipcDec | (branchDec & ~branchType) ? 4'b0 : aluOpDec;
      pcOf    <= luiDec ? 32'b0 : pcDec;
      immOf   <= (branchDec & ~branchType) ? 32'd4 : immDec;
    end
  end

  // ============================================================
  // select the operands to feed the alu and lsu
  // add the imm in rs1 to get the address
  // the data to store is in rs2


  reg [31:0] 	aluIn1, aluIn2;

  // propogate the valid, aluOp, rdWe, pc
  reg [31:0] 	pcOs;
  reg [3:0]		aluOpOs;
  reg 				validOs, rdWeOs;
  reg [4:0]		rdOs;
  reg 				lOs, sOs;
  reg [31:0]	lsuAddrOs, lsuDataOs;

  always @ (posedge clk or negedge rst_n) begin: OS
    if (!rst_n) begin 
      {pcOs, aluOpOs, validOs, rdWeOs, rdOs} <= 'b0;
      {aluIn1, aluIn2, lOs, sOs, lsuAddrOs, lsuDataOs} <= 'b0;
      {branch, branchTarget} <= 'b0;
    end else if (!stallPipe) begin 
      {pcOs, validOs, rdWeOs, rdOs} <= {pcOf, validOf, rdWeOf, rdOf};
      {lOs, sOs} <= {lOf, sOf};

      // the branch unit
      // 

      branch <= branchOf;

      lsuAddrOs <= rs1Data + immOf;
      lsuDataOs <= rs2Data;

      // when lui comes, the imm is the value 
      // so zero aluIn1 and set operation to add
      aluIn1	<= (luipcOf | branchOf) ? pcOf : rs1Data;

      // aluIn2 is between imm and rs2Data
      aluIn2	<= immSelOf ? immOf : rs2Data;

      // if IType and the operation is add then clear op[3],
      // coz there is no subi 
      if (immSelOf && (aluOpOf[2:0] == 3'b000))
        aluOpOs[3] <= 1'b0;
      else 
        aluOpOs[3] <= aluOpOf[3];

      aluOpOs[2:0] <= aluOpOf[2:0]; 
    end
  end

  // ============================================================
  // the execute stage
  // can have multiple units in paralell
  // for now we only have the alu and lsu 
  reg [31:0] exRes;

  // propogate the valid, pc, rdWe
  reg [31:0]	pcEx;
  reg [4:0]		rdEx;

  always @ (posedge clk or negedge rst_n) begin: EX
    if (!rst_n) begin 
      {pcEx, validEx, rdWeEx, rdEx, rdShiftEx} <= 'b0;
    end else if (!stallPipe) begin
      {pcEx, validEx, rdWeEx, rdEx} <= {pcOs, validOs, rdWeOs, rdOs};
      rdShiftEx <= 1 << rdOs;			
    end
  end

  // ============================================================
  // the alu has a fixed latency of 1
  // the alu causes no stalls
  reg [31:0]	aluRes;

  always @ (posedge clk or negedge rst_n) begin: EX_ALU
    if (!rst_n) begin 
      aluRes <= 'b0;
    end else begin 
      case (aluOpOs[2:0])
      3'b000: aluRes <= aluOpOs[3] ? aluIn1 - aluIn2 : aluIn1 + aluIn2;	// add/sub
      3'b001: aluRes <= aluIn1 << aluIn2[4:0];	// sll
      3'b010: aluRes <= $signed(aluIn1) < $signed(aluIn2) ? 32'b1 : 32'b0; 
      3'b011: aluRes <= aluIn1 < aluIn2 ? 32'b1 : 32'b0;
      3'b100: aluRes <= aluIn1 ^ aluIn2;
      3'b101: aluRes <= aluOpOs[3] ? $signed($signed(aluIn1) >>> aluIn2[4:0]) : aluIn1 >> aluIn2[4:0];
      3'b110: aluRes <= aluIn1 | aluIn2;
      3'b111: aluRes <= aluIn1 & aluIn2;
      endcase
    end 
  end

  // ============================================================
  // the lsu has min latency of 1 
  // max latency of infinity
  // lsu can stall the pipeline 
  // data to store in rs2

  reg [31:0]	lsuRes;
  reg 				lsuStall;
  reg [3:0]		lsuByteEn;
  reg 				lEx;

  assign oDbusAddr 		= lsuAddrOs;
  assign oDbusRead 		= lOs & validOs;
  assign oDbusWe	 		= sOs & validOs;
  assign oDbusData 		= lsuDataOs;
  assign oDbusByteEn 	= lsuByteEn;

  // wait only asserted when reading, writing does not assert wait
  // from m4k, reads have min latency of 1

  always @ (*) begin: EX_LSU_BYTEENABLE_GENERATOR
    lsuStall = iDbusWait & (lOs | sOs) & validOs;
  
    case (aluOpOs[1:0]) 
    2'b00:	lsuByteEn = 4'b1;			// sb/lb
    2'b01:	lsuByteEn = 4'b11;		// sh/lh
    2'b10:	lsuByteEn	= 4'b1111;	// sw/lw
    default:lsuByteEn = 4'b0;	
    endcase
  end

  always @ (posedge clk or negedge rst_n) begin: EX_LSU
    if (!rst_n) begin 
      lsuRes 	<= 'b0;
      lEx 		<= 'b0;
    end	else if (!stallPipe) begin 
      lEx 		<= lOs;
      if (aluOpOs[1]) begin  // lw
        lsuRes <= iDbusData;
      end else begin 
        case ({aluOpOs[2], aluOpOs[0]}) 
        2'b00: lsuRes <= { {24{iDbusData[07]}}, iDbusData[07:0] };	// lb
        2'b01: lsuRes <= { {16{iDbusData[15]}}, iDbusData[15:0] };	// lh
        2'b10: lsuRes <= { 24'b0, iDbusData[07:0] };	// lbu
        2'b11: lsuRes <= { 16'b0, iDbusData[15:0] };	// lhu 
        endcase
      end
    end
  end

  // ============================================================
  // the stall handling mech,
  // simply or the stalls from all the sources
  // for now, only lsu can stall
  // IF doesn't stall, it keeps sending invalid instructions
  // which don't affect anything

  always @ (*) begin: EX_LSU_STALL_GENERATOR
    stallPipe = lsuStall;
  end	

  // ============================================================
  // the write back stage

  // mux the result from various stages
  // for now, if load instruction, then select lsuRes
  always @ (*) begin: WB_MUX
    exRes	= lEx ? lsuRes : aluRes;
  end

  always @ (posedge clk) begin: WB_REGISTER_FILE
    // do not reset the register file
    // write back if valid only
    if (validEx && rdWeEx) begin 
      registers[rdEx] <= exRes;
    end
  end
endmodule

testbench/risac_tb_single_mem.v
`timescale 1ns / 1ps

module testbench();

  reg						clk = 1, rst_n = 0;
  wire	[31:0] 	oIbusAddr;
  reg		[31:0] 	iIbusData;
  reg		[31:0]	iIbusIAddr;
  reg						iIbusWait;
  
  wire	[31:0]	oDbusAddr;
  wire					oDbusWe;
  wire	[31:0]	oDbusData;
  wire					oDbusRead;
  wire	[3:0]		oDbusByteEn;
  reg		[31:0]	iDbusData;
  reg						iDbusWait;

  risac u_risac (
    .clk          (clk),
    .rst_n        (rst_n),

    // The IBUS

    .oIbusAddr    (oIbusAddr),
    .iIbusData    (iIbusData),
    .iIbusIAddr   (iIbusIAddr),
    .iIbusWait    (iIbusWait),
    
    // The DBUS

    .oDbusAddr    (oDbusAddr),
    .oDbusWe      (oDbusWe),
    .oDbusData    (oDbusData),
    .oDbusRead    (oDbusRead),
    .oDbusByteEn  (oDbusByteEn),
    .iDbusData    (iDbusData),
    .iDbusWait    (iDbusWait)
  );


  reg [7:0] mem [0:4095]; // 4K ram
  reg [31:0] cnt = 0;

  // create a clock
  always @ (posedge clk) begin 
    cnt = cnt + 1;
  end

  always begin 
    #10 
    clk = !clk;
  end

  // initialize the memories
  integer i;
  initial begin 
    // prepare a vcd dump
    $dumpfile("risac2.vcd");
    $dumpvars(0, testbench);
    $readmemh("program.vh", mem);

    $display ("\n======================");
    $display ("RISCV Virtual Terminal");
    $display ("======================\n"); 
    
    #5
    rst_n = 1'b1;



    #5000 
    // dump memory to output 
    $display ("======================\n"); 
    
    $finish;
  end

  // create a memory system
  // simple zero latency memory

  // ==========================
  // the instruction bus
  // ==========================

  always @ (oIbusAddr) begin 
    iIbusWait <= 1'b0;
    iIbusData <= {mem [oIbusAddr+3], mem [oIbusAddr+2], mem [oIbusAddr+1], mem [oIbusAddr]};
    iIbusIAddr<= oIbusAddr;
  end


  reg [7:0]  dmem_addr;
  reg [31:0] and_mask;

  always @ (cnt) begin 
    // the virtual console 
    if (oDbusWe && oDbusAddr == 32'h10000 && oDbusByteEn[0]) begin 
      $write("%c", oDbusData[7:0]);		
    end
  end 

  reg [31:0] oldWord;

  always @ (*) begin 
    iDbusData = 'b0;
    iDbusWait = 'b0;
    
    if (oDbusWe) begin 
      mem[oDbusAddr]     = oDbusByteEn[0] ? oDbusData[07:00] : mem[oDbusAddr];
      mem[oDbusAddr + 1] = oDbusByteEn[1] ? oDbusData[15:08] : mem[oDbusAddr + 1];
      mem[oDbusAddr + 2] = oDbusByteEn[2] ? oDbusData[23:16] : mem[oDbusAddr + 2];
      mem[oDbusAddr + 3] = oDbusByteEn[3] ? oDbusData[31:24] : mem[oDbusAddr + 3];
    end
    
    if (oDbusRead) begin 
      iDbusData = {mem[oDbusAddr + 3], mem[oDbusAddr + 2], mem[oDbusAddr + 1], mem[oDbusAddr]};
    end
  end

endmodule

testbench/risac.vcd
$date
	Mon Nov 18 22:07:50 2019
$end
$version
	Icarus Verilog
$end
$timescale
	1ps
$end
$scope module testbench $end
$var wire 32 ! oIbusAddr [31:0] $end
$var wire 1 " oDbusWe $end
$var wire 1 # oDbusRead $end
$var wire 32 $ oDbusData [31:0] $end
$var wire 4 % oDbusByteEn [3:0] $end
$var wire 32 & oDbusAddr [31:0] $end
$var reg 1 ' clk $end
$var reg 32 ( cnt [31:0] $end
$var reg 8 ) dmem_addr [7:0] $end
$var reg 32 * iDbusData [31:0] $end
$var reg 1 + iDbusWait $end
$var reg 32 , iIbusData [31:0] $end
$var reg 32 - iIbusIAddr [31:0] $end
$var reg 1 . iIbusWait $end
$var reg 32 / oldWord [31:0] $end
$var reg 1 0 rst_n $end
$var integer 32 1 i [31:0] $end
$scope module u_risac $end
$var wire 1 ' clk $end
$var wire 32 2 iDbusData [31:0] $end
$var wire 1 + iDbusWait $end
$var wire 32 3 iIbusData [31:0] $end
$var wire 32 4 iIbusIAddr [31:0] $end
$var wire 1 . iIbusWait $end
$var wire 32 5 oDbusAddr [31:0] $end
$var wire 4 6 oDbusByteEn [3:0] $end
$var wire 32 7 oDbusData [31:0] $end
$var wire 1 # oDbusRead $end
$var wire 1 " oDbusWe $end
$var wire 32 8 oIbusAddr [31:0] $end
$var wire 1 0 rst_n $end
$var wire 1 9 oIbusRead $end
$var reg 32 : aluIn1 [31:0] $end
$var reg 32 ; aluIn2 [31:0] $end
$var reg 4 < aluOpDec [3:0] $end
$var reg 4 = aluOpOf [3:0] $end
$var reg 4 > aluOpOs [3:0] $end
$var reg 32 ? aluRes [31:0] $end
$var reg 1 @ branch $end
$var reg 1 A branchDec $end
$var reg 1 B branchOf $end
$var reg 32 C branchTarget [31:0] $end
$var reg 1 D branchType $end
$var reg 1 E dataHazard $end
$var reg 32 F exRes [31:0] $end
$var reg 1 G falseAlarm $end
$var reg 1 H illegalDec $end
$var reg 32 I immDec [31:0] $end
$var reg 32 J immOf [31:0] $end
$var reg 1 K immSelDec $end
$var reg 1 L immSelOf $end
$var reg 1 M lDec $end
$var reg 1 N lEx $end
$var reg 1 O lOf $end
$var reg 1 P lOs $end
$var reg 32 Q lsuAddrOs [31:0] $end
$var reg 4 R lsuByteEn [3:0] $end
$var reg 32 S lsuDataOs [31:0] $end
$var reg 32 T lsuRes [31:0] $end
$var reg 1 U lsuStall $end
$var reg 1 V luiDec $end
$var reg 1 W luipcDec $end
$var reg 1 X luipcOf $end
$var reg 32 Y pc [31:0] $end
$var reg 1 Z pcChanged $end
$var reg 32 [ pcDec [31:0] $end
$var reg 32 \ pcEx [31:0] $end
$var reg 32 ] pcOf [31:0] $end
$var reg 32 ^ pcOs [31:0] $end
$var reg 5 _ rdDec [4:0] $end
$var reg 5 ` rdEx [4:0] $end
$var reg 5 a rdOf [4:0] $end
$var reg 5 b rdOs [4:0] $end
$var reg 32 c rdShiftDec [31:0] $end
$var reg 32 d rdShiftEx [31:0] $end
$var reg 1 e rdWeDec $end
$var reg 1 f rdWeEx $end
$var reg 1 g rdWeOf $end
$var reg 1 h rdWeOs $end
$var reg 32 i rs1Data [31:0] $end
$var reg 5 j rs1Dec [4:0] $end
$var reg 32 k rs1ShiftDec [31:0] $end
$var reg 1 l rs1booked $end
$var reg 32 m rs2Data [31:0] $end
$var reg 5 n rs2Dec [4:0] $end
$var reg 32 o rs2ShiftDec [31:0] $end
$var reg 1 p rs2booked $end
$var reg 1 q sDec $end
$var reg 1 r sOf $end
$var reg 1 s sOs $end
$var reg 1 t stallPipe $end
$var reg 1 u validDec $end
$var reg 1 v validEx $end
$var reg 1 w validOf $end
$var reg 1 x validOs $end
$var integer 32 y idx [31:0] $end
$scope begin DEC $end
$upscope $end
$scope begin EX $end
$upscope $end
$scope begin EX_ALU $end
$upscope $end
$scope begin EX_LSU $end
$upscope $end
$scope begin EX_LSU_BYTEENABLE_GENERATOR $end
$upscope $end
$scope begin EX_LSU_STALL_GENERATOR $end
$upscope $end
$scope begin HAZARD_DETECTION $end
$upscope $end
$scope begin IF $end
$upscope $end
$scope begin OF $end
$upscope $end
$scope begin OS $end
$upscope $end
$scope begin RAT $end
$upscope $end
$scope begin WB_MUX $end
$upscope $end
$scope begin WB_REGISTER_FILE $end
$upscope $end
$upscope $end
$upscope $end
$enddefinitions $end
#0
$dumpvars
bx y
0x
0w
0v
0u
0t
0s
0r
0q
0p
b0 o
b0 n
b0 m
0l
b0 k
b0 j
b0 i
0h
0g
0f
0e
b0 d
b0 c
b0 b
b0 a
b0 `
bx _
b0 ^
b0 ]
b0 \
b0 [
1Z
b0 Y
0X
0W
0V
0U
b0 T
b0 S
b1 R
b0 Q
0P
0O
0N
0M
0L
0K
b0 J
b0 I
0H
0G
b0 F
0E
0D
b0 C
0B
0A
0@
b0 ?
b0 >
b0 =
b0 <
b0 ;
b0 :
19
b0 8
b0 7
b1 6
b0 5
b0 4
b100100000000000010100010011 3
b0 2
bx 1
00
bx /
0.
b0 -
b100100000000000010100010011 ,
0+
b0 *
b0 )
b0 (
1'
b0 &
b1 %
b0 $
0#
0"
b0 !
$end
#5000
10
#10000
0'
#20000
b100 -
b100 4
b101000000010000000100011 ,
b101000000010000000100011 3
b1 d
bx a
b1001000 I
1K
1e
b10000000000 c
b1010 _
b100000000 o
b1 k
b1000 n
1D
1u
b100 !
b100 8
b100 Y
b1 (
b100000 y
1'
#30000
0'
#40000
b1000 -
b1000 4
b110010100000000010100010011 ,
b110010100000000010100010011 3
1E
1p
bx b
b1001000 J
bx m
1w
1L
b1010 a
1g
1q
b0 I
0K
0e
b1 c
b0 _
b10000000000 o
b1010 n
b10 <
b100 [
b1000 !
b1000 8
b1000 Y
b10 (
b100000 y
1'
#50000
0'
#60000
b10010 )
09
bx d
bx `
b1001000 ;
bx $
bx 7
bx S
b1001000 &
b1001000 5
b1001000 Q
1x
1h
b1010 b
b0 J
b100 ]
b10 =
0w
1r
0L
b0 a
0g
0Z
b11 (
b100000 y
1'
#70000
0'
#80000
b1001000 F
b0 )
b1111 %
b1111 6
b1111 R
b1001000 ?
b10000000000 d
1v
1f
b1010 `
b10 >
bx ;
b0 &
b0 5
b0 Q
1s
b100 ^
0x
0h
b0 b
b100 (
b100000 y
1'
#90000
0'
#100000
b0x F
0E
0p
b0x ?
b1 d
b100 \
0v
0f
b0 `
b101 (
b100000 y
1'
#110000
0'
#120000
b1100 -
b1100 4
b101000000010000000100011 ,
b101000000010000000100011 3
19
b1001000 m
1w
0q
b1100101 I
1K
1e
b10000000000 c
b1010 _
b100000 o
b101 n
b0 <
b1000 [
1Z
b1100 !
b1100 8
b1100 Y
b110 (
b100000 y
1'
#130000
0'
#140000
b10000 -
b10000 4
b110110000000000010100010011 ,
b110110000000000010100010011 3
b0 /
1"
1E
1p
b1001000 ;
b1001000 $
b1001000 7
b1001000 S
1x
b1100101 J
b1000 ]
b0 =
bx m
0r
1L
b1010 a
1g
1q
b0 I
0K
0e
b1 c
b0 _
b10000000000 o
b1010 n
b10 <
b1100 [
b10000 !
b10000 8
b10000 Y
b111 (
b100000 y
1'
#150000
0'
#160000
b1 F
b11001 )
b1 %
b1 6
b1 R
0"
09
b1 ?
1v
b0 >
b1100101 ;
bx $
bx 7
bx S
b1100101 &
b1100101 5
b1100101 Q
0s
b1000 ^
1h
b1010 b
b0 J
b1100 ]
b10 =
b1001000 m
0w
1r
0L
b0 a
0g
0Z
b1000 (
b100000 y
1'
#170000
0'
#180000
b1100101 F
b0 )
b1111 %
b1111 6
b1111 R
b1100101 ?
b10000000000 d
b1000 \
1f
b1010 `
b10 >
b1001000 ;
b1001000 $
b1001000 7
b1001000 S
b0 &
b0 5
b0 Q
1s
b1100 ^
0x
0h
b0 b
b1001 (
b100000 y
1'
#190000
0'
#200000
b1 F
0E
0p
b1 ?
b1 d
b1100 \
0v
0f
b0 `
b1010 (
b100000 y
1'
#210000
0'
#220000
b10100 -
b10100 4
b101000000010000000100011 ,
b101000000010000000100011 3
19
b1100101 m
1w
0q
b1101100 I
1K
1e
b10000000000 c
b1010 _
b1000000000000 o
b1100 n
b0 <
b10000 [
1Z
b10100 !
b10100 8
b10100 Y
b1011 (
b100000 y
1'
#230000
0'
#240000
b11000 -
b11000 4
b1001000 /
1"
1E
1p
b1100101 ;
b1100101 $
b1100101 7
b1100101 S
1x
b1101100 J
b10000 ]
b0 =
bx m
0r
1L
b1010 a
1g
1q
b0 I
0K
0e
b1 c
b0 _
b10000000000 o
b1010 n
b10 <
b10100 [
b11000 !
b11000 8
b11000 Y
b1100 (
b100000 y
1'
#250000
0'
#260000
b11011 )
b1 %
b1 6
b1 R
0"
09
1v
b0 >
b1101100 ;
bx $
bx 7
bx S
b1101100 &
b1101100 5
b1101100 Q
0s
b10000 ^
1h
b1010 b
b0 J
b10100 ]
b10 =
b1100101 m
0w
1r
0L
b0 a
0g
0Z
b1101 (
b100000 y
1'
#270000
0'
#280000
b1101100 F
b0 )
b1111 %
b1111 6
b1111 R
b1101100 ?
b10000000000 d
b10000 \
1f
b1010 `
b10 >
b1100101 ;
b1100101 $
b1100101 7
b1100101 S
b0 &
b0 5
b0 Q
1s
b10100 ^
0x
0h
b0 b
b1110 (
b100000 y
1'
#290000
0'
#300000
b1 F
0E
0p
b1 ?
b1 d
b10100 \
0v
0f
b0 `
b1111 (
b100000 y
1'
#310000
0'
#320000
b11100 -
b11100 4
b110111100000000010110010011 ,
b110111100000000010110010011 3
19
b1101100 m
1w
b11000 [
1Z
b11100 !
b11100 8
b11100 Y
b10000 (
b100000 y
1'
#330000
0'
#340000
b100000 -
b100000 4
b101100000010000000100011 ,
b101100000010000000100011 3
b1100101 /
1"
b1101100 ;
b1101100 $
b1101100 7
b1101100 S
1x
b11000 ]
0q
b1101111 I
1K
1e
b100000000000 c
b1011 _
b1000000000000000 o
b1111 n
b0 <
b11100 [
b100000 !
b100000 8
b100000 Y
b10001 (
b100000 y
1'
#350000
0'
#360000
b100100 -
b100100 4
b10110000000000011000010011 ,
b10110000000000011000010011 3
1E
1p
1v
b11000 ^
b1101111 J
b11100 ]
b0 =
bx m
0r
1L
b1011 a
1g
1q
b0 I
0K
0e
b1 c
b0 _
b100000000000 o
b1011 n
b10 <
b100000 [
b100100 !
b100100 8
b100100 Y
b10010 (
b100000 y
1'
#370000
0'
#380000
b11011 )
b1 %
b1 6
b1 R
0"
09
b11000 \
b0 >
b1101111 ;
bx $
bx 7
bx S
b1101111 &
b1101111 5
b1101111 Q
0s
b11100 ^
1h
b1011 b
b0 J
b100000 ]
b10 =
0w
1r
0L
b0 a
0g
0Z
b10011 (
b100000 y
1'
#390000
0'
#400000
b1101111 F
b0 )
b1111 %
b1111 6
b1111 R
b1101111 ?
b100000000000 d
b11100 \
1f
b1011 `
b10 >
bx ;
b0 &
b0 5
b0 Q
1s
b100000 ^
0x
0h
b0 b
b10100 (
b100000 y
1'
#410000
0'
#420000
b0x F
0E
0p
b0x ?
b1 d
b100000 \
0v
0f
b0 `
b10101 (
b100000 y
1'
#430000
0'
#440000
b101000 -
b101000 4
b110000000010000000100011 ,
b110000000010000000100011 3
19
b1101111 m
1w
0q
b101100 I
1K
1e
b1000000000000 c
b1100 _
b1000000000000 o
b1100 n
b0 <
b100100 [
1Z
b101000 !
b101000 8
b101000 Y
b10110 (
b100000 y
1'
#450000
0'
#460000
b101100 -
b101100 4
b10000000000000011000010011 ,
b10000000000000011000010011 3
b1101100 /
1"
1E
1p
b1101111 ;
b1101111 $
b1101111 7
b1101111 S
1x
b101100 J
b100100 ]
b0 =
bx m
0r
1L
b1100 a
1g
1q
b0 I
0K
0e
b1 c
b0 _
b10 <
b101000 [
b101100 !
b101100 8
b101100 Y
b10111 (
b100000 y
1'
#470000
0'
#480000
b1 F
b1011 )
b1 %
b1 6
b1 R
0"
09
b1 ?
1v
b0 >
b101100 ;
bx $
bx 7
bx S
b101100 &
b101100 5
b101100 Q
0s
b100100 ^
1h
b1100 b
b0 J
b101000 ]
b10 =
0w
1r
0L
b0 a
0g
0Z
b11000 (
b100000 y
1'
#490000
0'
#500000
b101100 F
b0 )
b1111 %
b1111 6
b1111 R
b101100 ?
b1000000000000 d
b100100 \
1f
b1100 `
b10 >
bx ;
b0 &
b0 5
b0 Q
1s
b101000 ^
0x
0h
b0 b
b11001 (
b100000 y
1'
#510000
0'
#520000
b0x F
0E
0p
b0x ?
b1 d
b101000 \
0v
0f
b0 `
b11010 (
b100000 y
1'
#530000
0'
#540000
b110000 -
b110000 4
b110000000010000000100011 ,
b110000000010000000100011 3
19
b101100 m
1w
0q
b100000 I
1K
1e
b1000000000000 c
b1100 _
b1 o
b0 n
b0 <
b101100 [
1Z
b110000 !
b110000 8
b110000 Y
b11011 (
b100000 y
1'
#550000
0'
